{"Update_Date":"2026-02-24 01:25:01","USD":{"Type":"Currency","Change":0.02,"Name":"Amerikan Doları","Buying":43.8282,"Selling":43.8611},"EUR":{"Type":"Currency","Change":0.01,"Name":"Euro","Buying":51.648,"Selling":51.7916},"GBP":{"Type":"Currency","Change":0.02,"Name":"İngiliz Sterlini","Buying":59.0564,"Selling":59.3381},"CHF":{"Name":"İsviçre Frangı","Buying":56.5598,"Type":"Currency","Selling":56.6608,"Change":0},"CAD":{"Name":"Kanada Doları","Buying":31.9914,"Type":"Currency","Selling":32.0341,"Change":0.07},"RUB":{"Name":"Rus Rublesi","Buying":0.5682,"Type":"Currency","Selling":0.5726,"Change":-0.08},"AED":{"Name":"BAE Dirhemi","Buying":11.9306,"Type":"Currency","Selling":11.9467,"Change":0.02},"AUD":{"Name":"Avustralya Doları","Buying":30.9076,"Type":"Currency","Selling":30.9528,"Change":-0.01},"DKK":{"Name":"Danimarka Kronu","Buying":6.9131,"Type":"Currency","Selling":6.9212,"Change":-0.01},"SEK":{"Name":"İsveç Kronu","Buying":4.8324,"Type":"Currency","Selling":4.8391,"Change":0.05},"NOK":{"Name":"Norveç Kronu","Buying":4.5716,"Type":"Currency","Selling":4.5858,"Change":-0.01},"JPY":{"Name":"Japon Yeni","Buying":0.002829,"Type":"Currency","Selling":0.002847,"Change":0},"KWD":{"Name":"Kuveyt Dinarı","Buying":142.6839,"Type":"Currency","Selling":143.2573,"Change":0.02},"ZAR":{"Name":"Güney Afrika Randı","Buying":2.7334,"Type":"Currency","Selling":2.7398,"Change":0.01},"BHD":{"Name":"Bahreyn Dinarı","Buying":116.2613,"Type":"Currency","Selling":116.3486,"Change":0.04},"LYD":{"Name":"Libya Dinarı","Buying":6.9457,"Type":"Currency","Selling":6.9509,"Change":0.81},"SAR":{"Name":"Suudi Arabistan Riyali","Buying":11.6688,"Type":"Currency","Selling":11.7044,"Change":0.02},"IQD":{"Name":"Irak Dinarı","Buying":0.0335,"Type":"Currency","Selling":0.0336,"Change":0.02},"ILS":{"Name":"İsrail Şekeli","Buying":14.0407,"Type":"Currency","Selling":14.0513,"Change":0.06},"IRR":{"Name":"İran Riyali","Buying":0.0001,"Type":"Currency","Selling":0.0001,"Change":-99.72},"INR":{"Name":"Hindistan Rupisi","Buying":0.4815,"Type":"Currency","Selling":0.4819,"Change":-0.02},"MXN":{"Name":"Meksika Pesosu","Buying":2.5371,"Type":"Currency","Selling":2.539,"Change":0.06},"HUF":{"Name":"Macar Forinti","Buying":0.1361,"Type":"Currency","Selling":0.1362,"Change":-0.01},"NZD":{"Name":"Yeni Zelanda Doları","Buying":26.096,"Type":"Currency","Selling":26.1156,"Change":0},"BRL":{"Name":"Brezilya Reali","Buying":8.4761,"Type":"Currency","Selling":8.4825,"Change":-0.01},"IDR":{"Name":"Endonezya Rupiahi","Buying":0.0026,"Type":"Currency","Selling":0.0026,"Change":0.18},"CZK":{"Name":"Çek Korunası","Buying":2.1329,"Type":"Currency","Selling":2.1345,"Change":0.04},"PLN":{"Name":"Polonya Zlotisi","Buying":12.2405,"Type":"Currency","Selling":12.2497,"Change":0},"RON":{"Name":"Romanya Leyi","Buying":10.1309,"Type":"Currency","Selling":10.15,"Change":-0.01},"CNY":{"Name":"Çin Yuanı","Buying":6.3596,"Type":"Currency","Selling":6.368,"Change":0},"ARS":{"Name":"Arjantin Pesosu","Buying":0.032,"Type":"Currency","Selling":0.032,"Change":0.02},"ALL":{"Name":"Arnavutluk Leki","Buying":0.5368,"Type":"Currency","Selling":0.5372,"Change":-0.01},"AZN":{"Name":"Azerbaycan Manatı","Buying":25.7813,"Type":"Currency","Selling":25.8006,"Change":0.02},"BAM":{"Name":"Bosna-Hersek Markı","Buying":26.436,"Type":"Currency","Selling":26.4558,"Change":2.34},"CLP":{"Name":"Şili Pesosu","Buying":0.0506,"Type":"Currency","Selling":0.0506,"Change":0.02},"COP":{"Name":"Kolombiya Pesosu","Buying":0.0119,"Type":"Currency","Selling":0.0119,"Change":0.07},"CRC":{"Name":"Kostarika Kolonu","Buying":0.0923,"Type":"Currency","Selling":0.0923,"Change":0.02},"DZD":{"Name":"Cezayir Dinarı","Buying":0.3371,"Type":"Currency","Selling":0.3373,"Change":-0.01},"EGP":{"Name":"Mısır Lirası","Buying":0.9184,"Type":"Currency","Selling":0.9191,"Change":-0.39},"HKD":{"Name":"Hong Kong Doları","Buying":5.6053,"Type":"Currency","Selling":5.6096,"Change":0.03},"ISK":{"Name":"İzlanda Kronası","Buying":0.3566,"Type":"Currency","Selling":0.3568,"Change":-0.01},"KRW":{"Name":"Güney Kore Wonu","Buying":0.0304,"Type":"Currency","Selling":0.0304,"Change":0.07},"KZT":{"Name":"Kazak Tengesi","Buying":0.0882,"Type":"Currency","Selling":0.0882,"Change":0.16},"LBP":{"Name":"Lübnan Lirası","Buying":0.0005,"Type":"Currency","Selling":0.0005,"Change":0.02},"LKR":{"Name":"Sri Lanka Rupisi","Buying":0.1417,"Type":"Currency","Selling":0.1418,"Change":0.01},"MAD":{"Name":"Fas Dirhemi","Buying":4.7767,"Type":"Currency","Selling":4.7802,"Change":0.07},"MDL":{"Name":"Moldovya Leusu","Buying":2.5827,"Type":"Currency","Selling":2.5846,"Change":0.02},"MKD":{"Name":"Makedon Dinarı","Buying":0.8391,"Type":"Currency","Selling":0.8398,"Change":-0.11},"MYR":{"Name":"Malezya Ringgiti","Buying":11.2652,"Type":"Currency","Selling":11.2736,"Change":0.32},"OMR":{"Name":"Umman Riyali","Buying":114.0023,"Type":"Currency","Selling":114.0879,"Change":0.02},"PEN":{"Name":"Peru İnti","Buying":13.083,"Type":"Currency","Selling":13.0929,"Change":0.02},"PHP":{"Name":"Filipinler Pesosu","Buying":0.7595,"Type":"Currency","Selling":0.7601,"Change":-0.01},"PKR":{"Name":"Pakistan Rupisi","Buying":0.1565,"Type":"Currency","Selling":0.1581,"Change":0.06},"QAR":{"Name":"Katar Riyali","Buying":11.6471,"Type":"Currency","Selling":12.5014,"Change":0.02},"RSD":{"Name":"Sırbistan Dinarı","Buying":0.4383,"Type":"Currency","Selling":0.4425,"Change":0},"SGD":{"Name":"Singapur Doları","Buying":34.6167,"Type":"Currency","Selling":34.6427,"Change":0.05},"SYP":{"Name":"Suriye Lirası","Buying":0.3795,"Type":"Currency","Selling":0.3797,"Change":0.02},"THB":{"Name":"Tayland Bahtı","Buying":1.4132,"Type":"Currency","Selling":1.4142,"Change":-0.05},"TWD":{"Name":"Yeni Tayvan Doları","Buying":1.394,"Type":"Currency","Selling":1.3951,"Change":0.05},"UAH":{"Name":"Ukrayna Grivnası","Buying":1.012,"Type":"Currency","Selling":1.0128,"Change":0.04},"UYU":{"Name":"Uruguay Pesosu","Buying":1.1325,"Type":"Currency","Selling":1.1334,"Change":0.02},"GEL":{"Name":"Gürcistan Larisi","Buying":16.3844,"Type":"Currency","Selling":16.3967,"Change":1.14},"TND":{"Name":"Tunus Dinarı","Buying":15.134,"Type":"Currency","Selling":15.1454,"Change":0.02},"BGN":{"Name":"Bulgar Levası","Buying":26.2504,"Type":"Currency","Selling":26.557,"Change":-0.13},"GRA":{"Selling":7371.3,"Type":"Gold","Name":"GRAMALTIN","Change":-0.12,"Buying":7370.21},"XU100":{"Selling":14061.71,"Type":"Gold","Name":"XU100","Change":0.92},"DBITCOIN":{"Selling":0,"Type":"Gold","Name":"DBITCOIN","Change":-4.08},"GUMUS":{"Selling":124.37,"Type":"Gold","Name":"GUMUS","Change":-0.77,"Buying":124.27},"BRENT":{"Selling":0,"Type":"Gold","Name":"BRENT","Change":-0.29},"ONS":{"Buying":0,"Type":"Gold","Name":"ONS","Selling":0,"Change":-0.15},"HAS":{"Buying":7333.35,"Type":"Gold","Name":"GRAMHASALTIN","Selling":7334.45,"Change":-0.12},"CEYREKALTIN":{"Buying":11883.52,"Type":"Gold","Name":"CEYREKALTIN","Selling":12167.83,"Change":0},"YARIMALTIN":{"Buying":23692.77,"Type":"Gold","Name":"YARIMALTIN","Selling":24335.66,"Change":0},"TAMALTIN":{"Buying":47534.08,"Type":"Gold","Name":"TAMALTIN","Selling":48522.49,"Change":0},"CUMHURIYETALTINI":{"Buying":49286,"Type":"Gold","Name":"CUMHURIYETALTINI","Selling":50034,"Change":0.12},"ATAALTIN":{"Buying":49019.52,"Type":"Gold","Name":"ATAALTIN","Selling":50308.59,"Change":0},"14AYARALTIN":{"Buying":4233.5,"Type":"Gold","Name":"14AYARALTIN","Selling":4242,"Change":0},"18AYARALTIN":{"Buying":5421.86,"Type":"Gold","Name":"18AYARALTIN","Selling":5432.73,"Change":0},"YIA":{"Buying":6773.61,"Type":"Gold","Name":"22AYARBILEZIK","Selling":6787.19,"Change":0},"IKIBUCUKALTIN":{"Buying":118835.2,"Type":"Gold","Name":"IKIBUCUKALTIN","Selling":120859.69,"Change":0},"BESLIALTIN":{"Buying":240641.28,"Type":"Gold","Name":"BESLIALTIN","Selling":245589.27,"Change":0},"GREMSEALTIN":{"Buying":118835.2,"Type":"Gold","Name":"GREMSEALTIN","Selling":121678.32,"Change":0},"RESATALTIN":{"Buying":49019.52,"Type":"Gold","Name":"RESATALTIN","Selling":50308.59,"Change":0},"HAMITALTIN":{"Buying":49019.52,"Type":"Gold","Name":"HAMITALTIN","Selling":50308.59,"Change":0},"GPL":{"Buying":3029.23,"Type":"Platinum","Name":"GRAMPLATIN","Selling":3049.16,"Change":-0.55},"PAL":{"Buying":2441.09,"Type":"Palladium","Name":"GRAMPALADYUM","Selling":2469.56,"Change":-0.54},"BTC":{"Name":"Bitcoin","USD_Price":64851,"TRY_Price":2844601,"Selling":2844601,"Change":-4.08,"Type":"CryptoCurrency"},"ETH":{"Name":"Ethereum","USD_Price":1865.44,"TRY_Price":81832,"Selling":81832,"Change":-4.51,"Type":"CryptoCurrency"},"USDT":{"Name":"Tether","USD_Price":0.999828,"TRY_Price":43.83,"Selling":43.83,"Change":0.03,"Type":"CryptoCurrency"},"XRP":{"Name":"Ripple","USD_Price":1.3638,"TRY_Price":59.82,"Selling":59.82,"Change":-2.33,"Type":"CryptoCurrency"},"BNB":{"Name":"BNB","USD_Price":597.49,"TRY_Price":26213,"Selling":26213,"Change":-2.93,"Type":"CryptoCurrency"},"USDC":{"Name":"USD Coin","USD_Price":1.0001,"TRY_Price":43.87,"Selling":43.87,"Change":-0.03,"Type":"CryptoCurrency"},"SOL":{"Name":"Solana","USD_Price":78.76,"TRY_Price":3453.7,"Selling":3453.7,"Change":-5.71,"Type":"CryptoCurrency"},"TRX":{"Name":"TRON","USD_Price":0.2814,"TRY_Price":12.335,"Selling":12.335,"Change":-3.3,"Type":"CryptoCurrency"},"DOGE":{"Name":"Dogecoin","USD_Price":0.09332,"TRY_Price":4.095,"Selling":4.095,"Change":-2.45,"Type":"CryptoCurrency"},"WBT":{"Name":"WhiteBIT Coin","USD_Price":48.35,"TRY_Price":2119.79,"Selling":2119.79,"Change":-3.91,"Type":"CryptoCurrency"},"BCH":{"Name":"Bitcoin Cash","USD_Price":502.8,"TRY_Price":22039,"Selling":22039,"Change":-12.13,"Type":"CryptoCurrency"},"USDS":{"Name":"USDS","USD_Price":0.999809,"TRY_Price":43.83,"Selling":43.83,"Change":-0.01,"Type":"CryptoCurrency"},"ADA":{"Name":"Cardano","USD_Price":0.2643,"TRY_Price":11.6,"Selling":11.6,"Change":-2.69,"Type":"CryptoCurrency"},"WBTC":{"Name":"Wrapped Bitcoin","USD_Price":64696.86,"TRY_Price":2836607.95,"Selling":2836607.95,"Change":-4.04,"Type":"CryptoCurrency"},"WBETH":{"Name":"Wrapped Beacon ETH","USD_Price":2032.08,"TRY_Price":89095.73,"Selling":89095.73,"Change":-4.51,"Type":"CryptoCurrency"},"LEO":{"Name":"LEO Token","USD_Price":8.17,"TRY_Price":358.38,"Selling":358.38,"Change":-0.28,"Type":"CryptoCurrency"},"HYPE":{"Name":"Hyperliquid","USD_Price":26.47,"TRY_Price":1160.49,"Selling":1160.49,"Change":-8.57,"Type":"CryptoCurrency"},"USDE":{"Name":"Ethena USDe","USD_Price":0.9993,"TRY_Price":43.8139,"Selling":43.8139,"Change":0,"Type":"CryptoCurrency"},"CC":{"Name":"Canton","USD_Price":0.161431,"TRY_Price":7.08,"Selling":7.08,"Change":1.22,"Type":"CryptoCurrency"},"LINK":{"Name":"Chainlink","USD_Price":8.32,"TRY_Price":365.4,"Selling":365.4,"Change":-4.26,"Type":"CryptoCurrency"},"XMR":{"Name":"Monero","USD_Price":309.14,"TRY_Price":13552.45,"Selling":13552.45,"Change":-5.08,"Type":"CryptoCurrency"},"XLM":{"Name":"Stellar","USD_Price":0.1524,"TRY_Price":6.686,"Selling":6.686,"Change":-1.87,"Type":"CryptoCurrency"},"USD1":{"Name":"USD1","USD_Price":0.9993,"TRY_Price":43.8139,"Selling":43.8139,"Change":-0.01,"Type":"CryptoCurrency"},"RAIN":{"Name":"Rain","USD_Price":0.00937793,"TRY_Price":0.411125,"Selling":0.411125,"Change":-2.75,"Type":"CryptoCurrency"},"DAI":{"Name":"Dai","USD_Price":0.999699,"TRY_Price":43.83,"Selling":43.83,"Change":-0.01,"Type":"CryptoCurrency"},"HBAR":{"Name":"Hedera","USD_Price":0.09532,"TRY_Price":4.186,"Selling":4.186,"Change":-2.26,"Type":"CryptoCurrency"},"PYUSD":{"Name":"PayPal USD","USD_Price":0.999694,"TRY_Price":43.83,"Selling":43.83,"Change":-0.03,"Type":"CryptoCurrency"},"LTC":{"Name":"Litecoin","USD_Price":51.87,"TRY_Price":2274,"Selling":2274,"Change":-3.08,"Type":"CryptoCurrency"},"ZEC":{"Name":"Zcash","USD_Price":239.72,"TRY_Price":10510.43,"Selling":10510.43,"Change":-2.79,"Type":"CryptoCurrency"},"AVAX":{"Name":"Avalanche","USD_Price":8.43,"TRY_Price":370.1,"Selling":370.1,"Change":-4.75,"Type":"CryptoCurrency"},"SHIB":{"Name":"Shiba Inu","USD_Price":1.0e-5,"TRY_Price":0.0002653,"Selling":0.0002653,"Change":-2.42,"Type":"CryptoCurrency"},"SUI":{"Name":"Sui","USD_Price":0.8863,"TRY_Price":38.89,"Selling":38.89,"Change":-4.02,"Type":"CryptoCurrency"},"TON":{"Name":"Toncoin","USD_Price":1.346,"TRY_Price":59,"Selling":59,"Change":0.07,"Type":"CryptoCurrency"},"WLFI":{"Name":"World Liberty Financial","USD_Price":0.1109,"TRY_Price":4.864,"Selling":4.864,"Change":-1.77,"Type":"CryptoCurrency"},"CRO":{"Name":"Cronos","USD_Price":0.0747,"TRY_Price":3.27,"Selling":3.27,"Change":-1.24,"Type":"CryptoCurrency"},"XAUT":{"Name":"Tether Gold","USD_Price":5205.06,"TRY_Price":228188,"Selling":228188,"Change":1.67,"Type":"CryptoCurrency"},"M":{"Name":"MemeCore","USD_Price":1.4,"TRY_Price":61.5,"Selling":61.5,"Change":3.87,"Type":"CryptoCurrency"},"PAXG":{"Name":"PAX Gold","USD_Price":5250.05,"TRY_Price":230220,"Selling":230220,"Change":1.68,"Type":"CryptoCurrency"},"UNI":{"Name":"Uniswap","USD_Price":3.374,"TRY_Price":148,"Selling":148,"Change":-2.93,"Type":"CryptoCurrency"},"DOT":{"Name":"Polkadot","USD_Price":1.274,"TRY_Price":56,"Selling":56,"Change":-3.04,"Type":"CryptoCurrency"},"MNT":{"Name":"Mantle","USD_Price":0.580568,"TRY_Price":25.45,"Selling":25.45,"Change":-3.97,"Type":"CryptoCurrency"},"USDF":{"Name":"Falcon USD","USD_Price":0.997161,"TRY_Price":43.72,"Selling":43.72,"Change":0.03,"Type":"CryptoCurrency"},"AAVE":{"Name":"Aave","USD_Price":115.3,"TRY_Price":5061,"Selling":5061,"Change":-2.45,"Type":"CryptoCurrency"},"ASTER":{"Name":"Aster","USD_Price":0.704,"TRY_Price":30.84,"Selling":30.84,"Change":1.3,"Type":"CryptoCurrency"},"PEPE":{"Name":"Pepe","USD_Price":0,"TRY_Price":0.00017546,"Selling":0.00017546,"Change":-0.99,"Type":"CryptoCurrency"},"USDG":{"Name":"Global Dollar","USD_Price":0.999879,"TRY_Price":43.83,"Selling":43.83,"Change":-0.01,"Type":"CryptoCurrency"},"TAO":{"Name":"Bittensor","USD_Price":171.4,"TRY_Price":7516,"Selling":7516,"Change":-1.27,"Type":"CryptoCurrency"},"BGB":{"Name":"Bitget Token","USD_Price":2.24,"TRY_Price":98.04,"Selling":98.04,"Change":-2.04,"Type":"CryptoCurrency"},"OKB":{"Name":"OKB","USD_Price":74.58,"TRY_Price":3269.49,"Selling":3269.49,"Change":-3.65,"Type":"CryptoCurrency"},"RLUSD":{"Name":"Ripple USD","USD_Price":1.0001,"TRY_Price":43.849,"Selling":43.849,"Change":-0.02,"Type":"CryptoCurrency"}}