{"Update_Date":"2026-04-14 14:35:01","USD":{"Buying":44.7277,"Type":"Currency","Selling":44.7414,"Change":0.11},"EUR":{"Buying":52.8049,"Type":"Currency","Selling":52.8181,"Change":0.44},"GBP":{"Buying":60.7272,"Type":"Currency","Selling":60.7445,"Change":0.56},"CHF":{"Buying":57.2991,"Type":"Currency","Selling":57.3387,"Change":0.54},"CAD":{"Buying":32.52,"Type":"Currency","Selling":32.5367,"Change":0.41},"RUB":{"Buying":0.5848,"Type":"Currency","Selling":0.5876,"Change":-0.13},"AED":{"Buying":12.1755,"Type":"Currency","Selling":12.1864,"Change":0.13},"AUD":{"Buying":31.8506,"Type":"Currency","Selling":31.8738,"Change":0.49},"DKK":{"Buying":7.0599,"Type":"Currency","Selling":7.0652,"Change":0.43},"SEK":{"Buying":4.8807,"Type":"Currency","Selling":4.8843,"Change":0.36},"NOK":{"Buying":4.7511,"Type":"Currency","Selling":4.7562,"Change":0.53},"JPY":{"Buying":0.002815,"Type":"Currency","Selling":0.002822,"Change":0.01},"KWD":{"Buying":144.4992,"Type":"Currency","Selling":145.0246,"Change":0.02},"ZAR":{"Buying":2.7331,"Type":"Currency","Selling":2.7348,"Change":0.44},"BHD":{"Buying":118.5593,"Type":"Currency","Selling":118.5957,"Change":0.12},"LYD":{"Buying":7.0626,"Type":"Currency","Selling":7.0648,"Change":0.69},"SAR":{"Buying":11.9052,"Type":"Currency","Selling":11.9361,"Change":0.11},"IQD":{"Buying":0.0342,"Type":"Currency","Selling":0.0342,"Change":0.13},"ILS":{"Buying":14.8237,"Type":"Currency","Selling":14.8283,"Change":0.83},"INR":{"Buying":0.4804,"Type":"Currency","Selling":0.4805,"Change":0.22},"MXN":{"Buying":2.5964,"Type":"Currency","Selling":2.5972,"Change":0.55},"HUF":{"Buying":0.1451,"Type":"Currency","Selling":0.1452,"Change":0.29},"NZD":{"Buying":26.3849,"Type":"Currency","Selling":26.393,"Change":0.65},"BRL":{"Buying":8.9577,"Type":"Currency","Selling":8.9605,"Change":0.17},"IDR":{"Buying":0.0026,"Type":"Currency","Selling":0.0026,"Change":0.08},"CZK":{"Buying":2.1661,"Type":"Currency","Selling":2.1668,"Change":0.42},"PLN":{"Buying":12.4375,"Type":"Currency","Selling":12.4413,"Change":0.47},"RON":{"Buying":10.3641,"Type":"Currency","Selling":10.374,"Change":0.42},"CNY":{"Buying":6.5673,"Type":"Currency","Selling":6.5699,"Change":0.24},"ARS":{"Buying":0.033,"Type":"Currency","Selling":0.033,"Change":0.11},"ALL":{"Buying":0.5506,"Type":"Currency","Selling":0.5508,"Change":0.83},"AZN":{"Buying":26.3104,"Type":"Currency","Selling":26.3185,"Change":0.11},"BAM":{"Buying":26.985,"Type":"Currency","Selling":26.9933,"Change":1.44},"CLP":{"Buying":0.05,"Type":"Currency","Selling":0.0501,"Change":0.11},"COP":{"Buying":0.0125,"Type":"Currency","Selling":0.0125,"Change":0.43},"CRC":{"Buying":0.097,"Type":"Currency","Selling":0.097,"Change":0.3},"DZD":{"Buying":0.3385,"Type":"Currency","Selling":0.3386,"Change":0.13},"EGP":{"Buying":0.8513,"Type":"Currency","Selling":0.8515,"Change":1.15},"HKD":{"Buying":5.7101,"Type":"Currency","Selling":5.7118,"Change":0.07},"ISK":{"Buying":0.367,"Type":"Currency","Selling":0.3672,"Change":0.17},"KRW":{"Buying":0.0304,"Type":"Currency","Selling":0.0304,"Change":0.71},"KZT":{"Buying":0.0941,"Type":"Currency","Selling":0.0942,"Change":0.05},"LBP":{"Buying":0.0005,"Type":"Currency","Selling":0.0005,"Change":0.14},"LKR":{"Buying":0.1417,"Type":"Currency","Selling":0.1418,"Change":0.09},"MAD":{"Buying":4.8372,"Type":"Currency","Selling":4.8386,"Change":0.24},"MDL":{"Buying":2.6096,"Type":"Currency","Selling":2.6104,"Change":-0.24},"MKD":{"Buying":0.8389,"Type":"Currency","Selling":0.8391,"Change":0.11},"MYR":{"Buying":11.3203,"Type":"Currency","Selling":11.3238,"Change":0.7},"OMR":{"Buying":116.3239,"Type":"Currency","Selling":116.3595,"Change":0.11},"PEN":{"Buying":13.2684,"Type":"Currency","Selling":13.2724,"Change":0.11},"PHP":{"Buying":0.7472,"Type":"Currency","Selling":0.7475,"Change":0.25},"PKR":{"Buying":0.1596,"Type":"Currency","Selling":0.1612,"Change":0.12},"QAR":{"Buying":11.8585,"Type":"Currency","Selling":12.7196,"Change":0.26},"RSD":{"Buying":0.4492,"Type":"Currency","Selling":0.4507,"Change":0.99},"SGD":{"Buying":35.1826,"Type":"Currency","Selling":35.1934,"Change":0.26},"SYP":{"Buying":0.3873,"Type":"Currency","Selling":0.3874,"Change":0.11},"THB":{"Buying":1.3962,"Type":"Currency","Selling":1.3966,"Change":0.19},"TWD":{"Buying":1.4163,"Type":"Currency","Selling":1.4168,"Change":0.33},"UAH":{"Buying":1.0277,"Type":"Currency","Selling":1.028,"Change":0.18},"UYU":{"Buying":1.1121,"Type":"Currency","Selling":1.1124,"Change":0.33},"GEL":{"Buying":16.6274,"Type":"Currency","Selling":16.6325,"Change":0.11},"TND":{"Buying":15.4127,"Type":"Currency","Selling":15.4174,"Change":-0.51},"BGN":{"Buying":26.7855,"Type":"Currency","Selling":27.0541,"Change":0.82},"GRA":{"Selling":6867.47,"Type":"Gold","Name":"GRAMALTIN","Change":0.79,"Buying":6866.62},"XU100":{"Selling":14191.8,"Type":"Gold","Name":"XU100","Change":0.95},"DBITCOIN":{"Selling":0,"Type":"Gold","Name":"DBITCOIN","Change":4.95},"GUMUS":{"Selling":111.36,"Type":"Gold","Name":"GUMUS","Change":2.49,"Buying":111.26},"BRENT":{"Selling":0,"Type":"Gold","Name":"BRENT","Change":1.05},"ONS":{"Buying":0,"Type":"Gold","Name":"ONS","Selling":0,"Change":0.68},"HAS":{"Buying":6832.29,"Type":"Gold","Name":"GRAMHASALTIN","Selling":6833.13,"Change":0.79},"CEYREKALTIN":{"Buying":10975.8,"Type":"Gold","Name":"CEYREKALTIN","Selling":11225.75,"Change":0.93},"YARIMALTIN":{"Buying":21883,"Type":"Gold","Name":"YARIMALTIN","Selling":22451.5,"Change":0.93},"TAMALTIN":{"Buying":43903.2,"Type":"Gold","Name":"TAMALTIN","Selling":44765.68,"Change":0.93},"CUMHURIYETALTINI":{"Buying":45495,"Type":"Gold","Name":"CUMHURIYETALTINI","Selling":46180,"Change":0.9},"ATAALTIN":{"Buying":45275.18,"Type":"Gold","Name":"ATAALTIN","Selling":46413.5,"Change":0.93},"14AYARALTIN":{"Buying":3910.13,"Type":"Gold","Name":"14AYARALTIN","Selling":3913.56,"Change":0.93},"18AYARALTIN":{"Buying":5007.71,"Type":"Gold","Name":"18AYARALTIN","Selling":5012.11,"Change":0.93},"YIA":{"Buying":6256.21,"Type":"Gold","Name":"22AYARBILEZIK","Selling":6261.7,"Change":0.93},"IKIBUCUKALTIN":{"Buying":109758,"Type":"Gold","Name":"IKIBUCUKALTIN","Selling":111502.25,"Change":0.93},"BESLIALTIN":{"Buying":222259.95,"Type":"Gold","Name":"BESLIALTIN","Selling":226574.77,"Change":0.93},"GREMSEALTIN":{"Buying":109758,"Type":"Gold","Name":"GREMSEALTIN","Selling":112257.5,"Change":0.93},"RESATALTIN":{"Buying":45275.18,"Type":"Gold","Name":"RESATALTIN","Selling":46413.5,"Change":0.93},"HAMITALTIN":{"Buying":45275.18,"Type":"Gold","Name":"HAMITALTIN","Selling":46413.5,"Change":0.93},"GPL":{"Buying":2985.15,"Type":"Platinum","Name":"GRAMPLATIN","Selling":2992.58,"Change":0.16},"PAL":{"Buying":2259.51,"Type":"Palladium","Name":"GRAMPALADYUM","Selling":2266.7,"Change":-0.27}}