{"Update_Date":"2026-02-17 15:03:01","USD":{"Type":"Currency","Change":0.05,"Name":"Amerikan Doları","Buying":43.7245,"Selling":43.7296},"EUR":{"Type":"Currency","Change":-0.15,"Name":"Euro","Buying":51.7618,"Selling":51.7707},"GBP":{"Type":"Currency","Change":-0.43,"Name":"İngiliz Sterlini","Buying":59.3495,"Selling":59.3596},"CHF":{"Name":"İsviçre Frangı","Buying":56.7409,"Type":"Currency","Selling":56.7696,"Change":-0.09},"CAD":{"Name":"Kanada Doları","Buying":32.0349,"Type":"Currency","Selling":32.0481,"Change":-0.04},"RUB":{"Name":"Rus Rublesi","Buying":0.5684,"Type":"Currency","Selling":0.5699,"Change":-0.05},"AED":{"Name":"BAE Dirhemi","Buying":11.9008,"Type":"Currency","Selling":11.911,"Change":0.05},"AUD":{"Name":"Avustralya Doları","Buying":30.8651,"Type":"Currency","Selling":30.8775,"Change":-0.17},"DKK":{"Name":"Danimarka Kronu","Buying":6.9218,"Type":"Currency","Selling":6.9258,"Change":-0.16},"SEK":{"Name":"İsveç Kronu","Buying":4.8626,"Type":"Currency","Selling":4.8671,"Change":-0.48},"NOK":{"Name":"Norveç Kronu","Buying":4.5931,"Type":"Currency","Selling":4.5962,"Change":-0.13},"JPY":{"Name":"Japon Yeni","Buying":0.002853,"Type":"Currency","Selling":0.0028599999999999997,"Change":0},"KWD":{"Name":"Kuveyt Dinarı","Buying":142.4584,"Type":"Currency","Selling":142.9558,"Change":0.12},"ZAR":{"Name":"Güney Afrika Randı","Buying":2.7246,"Type":"Currency","Selling":2.726,"Change":-0.36},"BHD":{"Name":"Bahreyn Dinarı","Buying":115.977,"Type":"Currency","Selling":115.9906,"Change":0.05},"LYD":{"Name":"Libya Dinarı","Buying":6.9247,"Type":"Currency","Selling":6.9255,"Change":0.78},"SAR":{"Name":"Suudi Arabistan Riyali","Buying":11.6443,"Type":"Currency","Selling":11.6741,"Change":0.05},"IQD":{"Name":"Irak Dinarı","Buying":0.0333,"Type":"Currency","Selling":0.0333,"Change":-0.06},"ILS":{"Name":"İsrail Şekeli","Buying":14.1193,"Type":"Currency","Selling":14.1209,"Change":-0.11},"IRR":{"Name":"İran Riyali","Buying":0.0001,"Type":"Currency","Selling":0.0001,"Change":-99.72},"INR":{"Name":"Hindistan Rupisi","Buying":0.4821,"Type":"Currency","Selling":0.4822,"Change":0.14},"MXN":{"Name":"Meksika Pesosu","Buying":2.5451,"Type":"Currency","Selling":2.5454,"Change":-0.05},"HUF":{"Name":"Macar Forinti","Buying":0.1369,"Type":"Currency","Selling":0.1369,"Change":-0.22},"NZD":{"Name":"Yeni Zelanda Doları","Buying":26.3989,"Type":"Currency","Selling":26.402,"Change":0.1},"BRL":{"Name":"Brezilya Reali","Buying":8.3693,"Type":"Currency","Selling":8.3703,"Change":0.08},"IDR":{"Name":"Endonezya Rupiahi","Buying":0.0026,"Type":"Currency","Selling":0.0026,"Change":0},"CZK":{"Name":"Çek Korunası","Buying":2.1314,"Type":"Currency","Selling":2.1316,"Change":-0.17},"PLN":{"Name":"Polonya Zlotisi","Buying":12.2698,"Type":"Currency","Selling":12.2712,"Change":-0.22},"RON":{"Name":"Romanya Leyi","Buying":10.1458,"Type":"Currency","Selling":10.1539,"Change":-0.17},"CNY":{"Name":"Çin Yuanı","Buying":6.3484,"Type":"Currency","Selling":6.35,"Change":0.02},"ARS":{"Name":"Arjantin Pesosu","Buying":0.0312,"Type":"Currency","Selling":0.0313,"Change":0.05},"ALL":{"Name":"Arnavutluk Leki","Buying":0.5368,"Type":"Currency","Selling":0.5369,"Change":-0.16},"AZN":{"Name":"Azerbaycan Manatı","Buying":25.7203,"Type":"Currency","Selling":25.7233,"Change":0.05},"BAM":{"Name":"Bosna-Hersek Markı","Buying":26.4804,"Type":"Currency","Selling":26.4835,"Change":2.79},"CLP":{"Name":"Şili Pesosu","Buying":0.0504,"Type":"Currency","Selling":0.0504,"Change":-0.38},"COP":{"Name":"Kolombiya Pesosu","Buying":0.0119,"Type":"Currency","Selling":0.0119,"Change":0.03},"CRC":{"Name":"Kostarika Kolonu","Buying":0.0908,"Type":"Currency","Selling":0.0909,"Change":0.16},"DZD":{"Name":"Cezayir Dinarı","Buying":0.3369,"Type":"Currency","Selling":0.337,"Change":-0.01},"EGP":{"Name":"Mısır Lirası","Buying":0.93,"Type":"Currency","Selling":0.9301,"Change":-0.59},"HKD":{"Name":"Hong Kong Doları","Buying":5.5948,"Type":"Currency","Selling":5.5955,"Change":0.05},"ISK":{"Name":"İzlanda Kronası","Buying":0.3569,"Type":"Currency","Selling":0.3569,"Change":-0.11},"KRW":{"Name":"Güney Kore Wonu","Buying":0.0303,"Type":"Currency","Selling":0.0303,"Change":-0.02},"KZT":{"Name":"Kazak Tengesi","Buying":0.0891,"Type":"Currency","Selling":0.0891,"Change":0.18},"LBP":{"Name":"Lübnan Lirası","Buying":0.0005,"Type":"Currency","Selling":0.0005,"Change":-0.05},"LKR":{"Name":"Sri Lanka Rupisi","Buying":0.1413,"Type":"Currency","Selling":0.1414,"Change":0},"MAD":{"Name":"Fas Dirhemi","Buying":4.7871,"Type":"Currency","Selling":4.7877,"Change":-0.03},"MDL":{"Name":"Moldovya Leusu","Buying":2.5755,"Type":"Currency","Selling":2.5758,"Change":-0.58},"MKD":{"Name":"Makedon Dinarı","Buying":0.8394,"Type":"Currency","Selling":0.8395,"Change":-0.12},"MYR":{"Name":"Malezya Ringgiti","Buying":11.2114,"Type":"Currency","Selling":11.2127,"Change":0.05},"OMR":{"Name":"Umman Riyali","Buying":113.7208,"Type":"Currency","Selling":113.734,"Change":0.05},"PEN":{"Name":"Peru İnti","Buying":13.021,"Type":"Currency","Selling":13.0225,"Change":-0.07},"PHP":{"Name":"Filipinler Pesosu","Buying":0.7551,"Type":"Currency","Selling":0.7552,"Change":0.12},"PKR":{"Name":"Pakistan Rupisi","Buying":0.1554,"Type":"Currency","Selling":0.157,"Change":-0.06},"QAR":{"Name":"Katar Riyali","Buying":11.5765,"Type":"Currency","Selling":12.412,"Change":-0.07},"RSD":{"Name":"Sırbistan Dinarı","Buying":0.4413,"Type":"Currency","Selling":0.4428,"Change":0.02},"SGD":{"Name":"Singapur Doları","Buying":34.6113,"Type":"Currency","Selling":34.6154,"Change":-0.03},"SYP":{"Name":"Suriye Lirası","Buying":0.3785,"Type":"Currency","Selling":0.3786,"Change":0.05},"THB":{"Name":"Tayland Bahtı","Buying":1.3971,"Type":"Currency","Selling":1.3972,"Change":-0.49},"TWD":{"Name":"Yeni Tayvan Doları","Buying":1.3929,"Type":"Currency","Selling":1.3931,"Change":-0.04},"UAH":{"Name":"Ukrayna Grivnası","Buying":1.01,"Type":"Currency","Selling":1.0102,"Change":-0.05},"UYU":{"Name":"Uruguay Pesosu","Buying":1.1269,"Type":"Currency","Selling":1.1271,"Change":-0.08},"GEL":{"Name":"Gürcistan Larisi","Buying":16.3456,"Type":"Currency","Selling":16.3475,"Change":1.17},"TND":{"Name":"Tunus Dinarı","Buying":15.1401,"Type":"Currency","Selling":15.1418,"Change":-0.09},"BGN":{"Name":"Bulgar Levası","Buying":26.3928,"Type":"Currency","Selling":26.6379,"Change":-0.11},"GRA":{"Selling":6932.78,"Type":"Gold","Name":"GRAMALTIN","Change":-1.18,"Buying":6931.88},"XU100":{"Selling":14333.14,"Type":"Gold","Name":"XU100","Change":-0.04},"DBITCOIN":{"Selling":0,"Type":"Gold","Name":"DBITCOIN","Change":-1.43},"GUMUS":{"Selling":105.13,"Type":"Gold","Name":"GUMUS","Change":-2.39,"Buying":105.03},"BRENT":{"Selling":0,"Type":"Gold","Name":"BRENT","Change":0.13},"ONS":{"Buying":0,"Type":"Gold","Name":"ONS","Selling":0,"Change":-1.24},"HAS":{"Buying":6897.22,"Type":"Gold","Name":"GRAMHASALTIN","Selling":6898.11,"Change":-1.18},"CEYREKALTIN":{"Buying":11622.11,"Type":"Gold","Name":"CEYREKALTIN","Selling":11893.44,"Change":-0.43},"YARIMALTIN":{"Buying":23171.58,"Type":"Gold","Name":"YARIMALTIN","Selling":23786.88,"Change":-0.43},"TAMALTIN":{"Buying":46488.44,"Type":"Gold","Name":"TAMALTIN","Selling":47428.27,"Change":-0.43},"CUMHURIYETALTINI":{"Buying":48054,"Type":"Gold","Name":"CUMHURIYETALTINI","Selling":48789,"Change":-0.69},"ATAALTIN":{"Buying":47941.21,"Type":"Gold","Name":"ATAALTIN","Selling":49174.1,"Change":-0.43},"14AYARALTIN":{"Buying":4140.38,"Type":"Gold","Name":"14AYARALTIN","Selling":4146.34,"Change":-0.43},"18AYARALTIN":{"Buying":5302.59,"Type":"Gold","Name":"18AYARALTIN","Selling":5310.22,"Change":-0.43},"YIA":{"Buying":6624.6,"Type":"Gold","Name":"22AYARBILEZIK","Selling":6634.14,"Change":-0.43},"IKIBUCUKALTIN":{"Buying":116221.1,"Type":"Gold","Name":"IKIBUCUKALTIN","Selling":118134.23,"Change":-0.43},"BESLIALTIN":{"Buying":235347.74,"Type":"Gold","Name":"BESLIALTIN","Selling":240051.08,"Change":-0.43},"GREMSEALTIN":{"Buying":116221.1,"Type":"Gold","Name":"GREMSEALTIN","Selling":118934.4,"Change":-0.43},"RESATALTIN":{"Buying":47941.21,"Type":"Gold","Name":"RESATALTIN","Selling":49174.1,"Change":-0.43},"HAMITALTIN":{"Buying":47941.21,"Type":"Gold","Name":"HAMITALTIN","Selling":49174.1,"Change":-0.43},"GPL":{"Buying":2827.44,"Type":"Platinum","Name":"GRAMPLATIN","Selling":2836.76,"Change":-1.64},"PAL":{"Buying":2349.24,"Type":"Palladium","Name":"GRAMPALADYUM","Selling":2361.26,"Change":-3.08},"BTC":{"Name":"Bitcoin","USD_Price":67883,"TRY_Price":2965889,"Selling":2965889,"Change":-1.42,"Type":"CryptoCurrency"},"ETH":{"Name":"Ethereum","USD_Price":1968.47,"TRY_Price":86013,"Selling":86013,"Change":-0.45,"Type":"CryptoCurrency"},"USDT":{"Name":"Tether","USD_Price":0.999516,"TRY_Price":43.71,"Selling":43.71,"Change":-0.01,"Type":"CryptoCurrency"},"XRP":{"Name":"Ripple","USD_Price":1.452,"TRY_Price":63.42,"Selling":63.42,"Change":-2.26,"Type":"CryptoCurrency"},"BNB":{"Name":"BNB","USD_Price":618.43,"TRY_Price":27014,"Selling":27014,"Change":-0.1,"Type":"CryptoCurrency"},"USDC":{"Name":"USD Coin","USD_Price":1.0004,"TRY_Price":43.71,"Selling":43.71,"Change":-0.01,"Type":"CryptoCurrency"},"SOL":{"Name":"Solana","USD_Price":85.13,"TRY_Price":3718.7,"Selling":3718.7,"Change":-0.56,"Type":"CryptoCurrency"},"TRX":{"Name":"TRON","USD_Price":0.2812,"TRY_Price":12.285,"Selling":12.285,"Change":0.21,"Type":"CryptoCurrency"},"DOGE":{"Name":"Dogecoin","USD_Price":0.09887,"TRY_Price":4.319,"Selling":4.319,"Change":-2.92,"Type":"CryptoCurrency"},"BCH":{"Name":"Bitcoin Cash","USD_Price":557.7,"TRY_Price":24408,"Selling":24408,"Change":-0.16,"Type":"CryptoCurrency"},"WBT":{"Name":"WhiteBIT Coin","USD_Price":51.18,"TRY_Price":2237,"Selling":2237,"Change":-0.37,"Type":"CryptoCurrency"},"ADA":{"Name":"Cardano","USD_Price":0.2805,"TRY_Price":12.25,"Selling":12.25,"Change":-1.02,"Type":"CryptoCurrency"},"USDS":{"Name":"USDS","USD_Price":0.99992,"TRY_Price":43.73,"Selling":43.73,"Change":0.03,"Type":"CryptoCurrency"},"WBTC":{"Name":"Wrapped Bitcoin","USD_Price":67755.77,"TRY_Price":2962776.88,"Selling":2962776.88,"Change":-1.34,"Type":"CryptoCurrency"},"WBETH":{"Name":"Wrapped Beacon ETH","USD_Price":2145.34,"TRY_Price":93809.93,"Selling":93809.93,"Change":-0.4,"Type":"CryptoCurrency"},"LEO":{"Name":"LEO Token","USD_Price":8.67,"TRY_Price":379.39,"Selling":379.39,"Change":2.35,"Type":"CryptoCurrency"},"HYPE":{"Name":"Hyperliquid","USD_Price":29.34,"TRY_Price":1282.63,"Selling":1282.63,"Change":-2.06,"Type":"CryptoCurrency"},"CC":{"Name":"Canton","USD_Price":0.166787,"TRY_Price":7.29,"Selling":7.29,"Change":3.22,"Type":"CryptoCurrency"},"USDE":{"Name":"Ethena USDe","USD_Price":0.9995,"TRY_Price":43.7054,"Selling":43.7054,"Change":0,"Type":"CryptoCurrency"},"LINK":{"Name":"Chainlink","USD_Price":8.77,"TRY_Price":383,"Selling":383,"Change":-0.45,"Type":"CryptoCurrency"},"XMR":{"Name":"Monero","USD_Price":331.52,"TRY_Price":14476.4,"Selling":14476.4,"Change":0.96,"Type":"CryptoCurrency"},"XLM":{"Name":"Stellar","USD_Price":0.1658,"TRY_Price":7.234,"Selling":7.234,"Change":-2.01,"Type":"CryptoCurrency"},"USD1":{"Name":"USD1","USD_Price":1.0003,"TRY_Price":43.7404,"Selling":43.7404,"Change":0.09,"Type":"CryptoCurrency"},"ZEC":{"Name":"Zcash","USD_Price":293.6,"TRY_Price":12838.3,"Selling":12838.3,"Change":-0.56,"Type":"CryptoCurrency"},"RAIN":{"Name":"Rain","USD_Price":0.00978466,"TRY_Price":0.427913,"Selling":0.427913,"Change":1.62,"Type":"CryptoCurrency"},"HBAR":{"Name":"Hedera","USD_Price":0.09983,"TRY_Price":4.363,"Selling":4.363,"Change":-0.82,"Type":"CryptoCurrency"},"LTC":{"Name":"Litecoin","USD_Price":54.97,"TRY_Price":2402,"Selling":2402,"Change":1.93,"Type":"CryptoCurrency"},"DAI":{"Name":"Dai","USD_Price":0.999876,"TRY_Price":43.73,"Selling":43.73,"Change":0.02,"Type":"CryptoCurrency"},"PYUSD":{"Name":"PayPal USD","USD_Price":0.999982,"TRY_Price":43.74,"Selling":43.74,"Change":0.03,"Type":"CryptoCurrency"},"AVAX":{"Name":"Avalanche","USD_Price":9.12,"TRY_Price":398.3,"Selling":398.3,"Change":-1.72,"Type":"CryptoCurrency"},"SHIB":{"Name":"Shiba Inu","USD_Price":1.0e-5,"TRY_Price":0.000284,"Selling":0.000284,"Change":-1.06,"Type":"CryptoCurrency"},"SUI":{"Name":"Sui","USD_Price":0.969,"TRY_Price":42.35,"Selling":42.35,"Change":0.57,"Type":"CryptoCurrency"},"TON":{"Name":"Toncoin","USD_Price":1.428,"TRY_Price":62.4,"Selling":62.4,"Change":-1.52,"Type":"CryptoCurrency"},"CRO":{"Name":"Cronos","USD_Price":0.079448,"TRY_Price":3.47,"Selling":3.47,"Change":0.09,"Type":"CryptoCurrency"},"WLFI":{"Name":"World Liberty Financial","USD_Price":0.0999,"TRY_Price":4.364,"Selling":4.364,"Change":-2.16,"Type":"CryptoCurrency"},"M":{"Name":"MemeCore","USD_Price":1.47,"TRY_Price":64.36,"Selling":64.36,"Change":14.1,"Type":"CryptoCurrency"},"XAUT":{"Name":"Tether Gold","USD_Price":4906.52,"TRY_Price":214518,"Selling":214518,"Change":-1.46,"Type":"CryptoCurrency"},"DOT":{"Name":"Polkadot","USD_Price":1.363,"TRY_Price":59.4,"Selling":59.4,"Change":0.44,"Type":"CryptoCurrency"},"PAXG":{"Name":"PAX Gold","USD_Price":4933.27,"TRY_Price":215618,"Selling":215618,"Change":-1.55,"Type":"CryptoCurrency"},"UNI":{"Name":"Uniswap","USD_Price":3.52,"TRY_Price":153.8,"Selling":153.8,"Change":0.6,"Type":"CryptoCurrency"},"MNT":{"Name":"Mantle","USD_Price":0.636707,"TRY_Price":27.84,"Selling":27.84,"Change":0.86,"Type":"CryptoCurrency"},"AAVE":{"Name":"Aave","USD_Price":124.59,"TRY_Price":5445,"Selling":5445,"Change":-1.56,"Type":"CryptoCurrency"},"PEPE":{"Name":"Pepe","USD_Price":0,"TRY_Price":0.00019153,"Selling":0.00019153,"Change":-2.67,"Type":"CryptoCurrency"},"TAO":{"Name":"Bittensor","USD_Price":190.8,"TRY_Price":8341,"Selling":8341,"Change":0,"Type":"CryptoCurrency"},"USDF":{"Name":"Falcon USD","USD_Price":0.997664,"TRY_Price":43.62,"Selling":43.62,"Change":0.07,"Type":"CryptoCurrency"},"ASTER":{"Name":"Aster","USD_Price":0.705,"TRY_Price":30.81,"Selling":30.81,"Change":-1.26,"Type":"CryptoCurrency"},"OKB":{"Name":"OKB","USD_Price":79.3,"TRY_Price":3467.8,"Selling":3467.8,"Change":0.33,"Type":"CryptoCurrency"},"BGB":{"Name":"Bitget Token","USD_Price":2.37,"TRY_Price":103.75,"Selling":103.75,"Change":-0.47,"Type":"CryptoCurrency"},"PI":{"Name":"Pi Network","USD_Price":0.178762,"TRY_Price":7.81,"Selling":7.81,"Change":5.41,"Type":"CryptoCurrency"},"USDG":{"Name":"Global Dollar","USD_Price":0.999766,"TRY_Price":43.72,"Selling":43.72,"Change":0.01,"Type":"CryptoCurrency"}}