{"Update_Date":"2026-04-23 13:02:02","USD":{"Buying":44.9216,"Type":"Currency","Selling":44.9276,"Change":0.01},"EUR":{"Buying":52.6483,"Type":"Currency","Selling":52.6597,"Change":0.14},"GBP":{"Buying":60.7652,"Type":"Currency","Selling":60.8159,"Change":0.22},"CHF":{"Buying":57.2003,"Type":"Currency","Selling":57.2349,"Change":-0.05},"CAD":{"Buying":32.8622,"Type":"Currency","Selling":32.8768,"Change":0.04},"RUB":{"Buying":0.5986,"Type":"Currency","Selling":0.6,"Change":0.15},"AED":{"Buying":12.2275,"Type":"Currency","Selling":12.2379,"Change":0.03},"AUD":{"Buying":32.1039,"Type":"Currency","Selling":32.12,"Change":-0.17},"DKK":{"Buying":7.0284,"Type":"Currency","Selling":7.0319,"Change":-0.09},"SEK":{"Buying":4.8629,"Type":"Currency","Selling":4.8656,"Change":-0.23},"NOK":{"Buying":4.8099,"Type":"Currency","Selling":4.8127,"Change":-0.35},"JPY":{"Buying":0.0028139999999999997,"Type":"Currency","Selling":0.0028239999999999997,"Change":0},"KWD":{"Buying":145.7176,"Type":"Currency","Selling":146.2263,"Change":0.19},"ZAR":{"Buying":2.7112,"Type":"Currency","Selling":2.7136,"Change":-0.55},"BHD":{"Buying":118.985,"Type":"Currency","Selling":119.0009,"Change":-0.1},"LYD":{"Buying":7.0854,"Type":"Currency","Selling":7.0864,"Change":-0.31},"SAR":{"Buying":11.9621,"Type":"Currency","Selling":11.9929,"Change":0.01},"IQD":{"Buying":0.0342,"Type":"Currency","Selling":0.0342,"Change":-0.33},"ILS":{"Buying":14.9345,"Type":"Currency","Selling":14.9365,"Change":-0.44},"INR":{"Buying":0.4774,"Type":"Currency","Selling":0.4774,"Change":-0.28},"MXN":{"Buying":2.5833,"Type":"Currency","Selling":2.5837,"Change":-0.31},"HUF":{"Buying":0.1436,"Type":"Currency","Selling":0.1436,"Change":-0.38},"NZD":{"Buying":26.4089,"Type":"Currency","Selling":26.4125,"Change":-0.42},"BRL":{"Buying":9.0444,"Type":"Currency","Selling":9.0456,"Change":-0.07},"IDR":{"Buying":0.0026,"Type":"Currency","Selling":0.0026,"Change":-0.62},"CZK":{"Buying":2.1557,"Type":"Currency","Selling":2.156,"Change":-0.17},"PLN":{"Buying":12.3605,"Type":"Currency","Selling":12.3621,"Change":-0.2},"RON":{"Buying":10.3111,"Type":"Currency","Selling":10.3199,"Change":-0.17},"CNY":{"Buying":6.5701,"Type":"Currency","Selling":6.5722,"Change":-0.06},"ARS":{"Buying":0.0326,"Type":"Currency","Selling":0.0326,"Change":0},"ALL":{"Buying":0.5502,"Type":"Currency","Selling":0.5502,"Change":-0.08},"AZN":{"Name":"AZERBAYCAN YENİ MANATI","Buying":2643,"Selling":2643,"Change":0,"Type":"Currency"},"BAM":{"Buying":26.9783,"Type":"Currency","Selling":26.9819,"Change":-0.14},"CLP":{"Buying":0.0506,"Type":"Currency","Selling":0.0506,"Change":0.05},"COP":{"Buying":0.0126,"Type":"Currency","Selling":0.0126,"Change":-0.01},"CRC":{"Buying":0.0986,"Type":"Currency","Selling":0.0986,"Change":0.07},"DZD":{"Buying":0.3389,"Type":"Currency","Selling":0.3389,"Change":-0.05},"EGP":{"Buying":0.8545,"Type":"Currency","Selling":0.8546,"Change":-1.05},"HKD":{"Buying":5.7356,"Type":"Currency","Selling":5.7363,"Change":0.02},"ISK":{"Buying":0.3653,"Type":"Currency","Selling":0.3654,"Change":-0.11},"KRW":{"Buying":0.0304,"Type":"Currency","Selling":0.0304,"Change":0},"KZT":{"Buying":0.0969,"Type":"Currency","Selling":0.0969,"Change":-0.07},"LBP":{"Buying":0.0005,"Type":"Currency","Selling":0.0005,"Change":-0.34},"LKR":{"Buying":0.1415,"Type":"Currency","Selling":0.1416,"Change":-0.16},"MAD":{"Buying":4.8428,"Type":"Currency","Selling":4.8434,"Change":-0.11},"MDL":{"Buying":2.5987,"Type":"Currency","Selling":2.5991,"Change":-0.84},"MKD":{"Buying":0.8519,"Type":"Currency","Selling":0.852,"Change":-0.34},"MYR":{"Buying":11.3324,"Type":"Currency","Selling":11.3339,"Change":-0.29},"OMR":{"Buying":116.8342,"Type":"Currency","Selling":116.8499,"Change":0.01},"PEN":{"Buying":13.0283,"Type":"Currency","Selling":13.03,"Change":-0.28},"PHP":{"Buying":0.7428,"Type":"Currency","Selling":0.7429,"Change":-0.41},"PKR":{"Buying":0.1598,"Type":"Currency","Selling":0.1614,"Change":-0.25},"QAR":{"Buying":11.8626,"Type":"Currency","Selling":12.7266,"Change":-0.24},"RSD":{"Buying":0.4479,"Type":"Currency","Selling":0.4489,"Change":0.04},"SGD":{"Buying":35.1885,"Type":"Currency","Selling":35.1932,"Change":-0.06},"SYP":{"Buying":0.3889,"Type":"Currency","Selling":0.389,"Change":0.01},"THB":{"Buying":1.384,"Type":"Currency","Selling":1.3842,"Change":-0.68},"TWD":{"Buying":1.4229,"Type":"Currency","Selling":1.4231,"Change":-0.28},"UAH":{"Buying":1.0225,"Type":"Currency","Selling":1.0227,"Change":-0.02},"UYU":{"Buying":1.1261,"Type":"Currency","Selling":1.1263,"Change":-0.3},"GEL":{"Buying":16.6995,"Type":"Currency","Selling":16.7017,"Change":0.01},"TND":{"Buying":15.3999,"Type":"Currency","Selling":15.402,"Change":-1.47},"BGN":{"Buying":26.8282,"Type":"Currency","Selling":27.0705,"Change":-0.1},"GRA":{"Selling":6787.31,"Type":"Gold","Name":"GRAMALTIN","Change":-0.85,"Buying":6786.5},"XU100":{"Selling":14335.49,"Type":"Gold","Name":"XU100","Change":-0.28},"DBITCOIN":{"Selling":0,"Type":"Gold","Name":"DBITCOIN","Change":-0.48},"GUMUS":{"Selling":108.92,"Type":"Gold","Name":"GUMUS","Change":-2.98,"Buying":108.83},"BRENT":{"Selling":0,"Type":"Gold","Name":"BRENT","Change":1.91},"ONS":{"Buying":0,"Type":"Gold","Name":"ONS","Selling":0,"Change":-0.85},"HAS":{"Buying":6752.56,"Type":"Gold","Name":"GRAMHASALTIN","Selling":6753.37,"Change":-0.85},"CEYREKALTIN":{"Buying":10895.19,"Type":"Gold","Name":"CEYREKALTIN","Selling":11145.86,"Change":-0.91},"YARIMALTIN":{"Buying":21722.28,"Type":"Gold","Name":"YARIMALTIN","Selling":22291.72,"Change":-0.91},"TAMALTIN":{"Buying":43580.74,"Type":"Gold","Name":"TAMALTIN","Selling":44447.1,"Change":-0.91},"CUMHURIYETALTINI":{"Buying":45116,"Type":"Gold","Name":"CUMHURIYETALTINI","Selling":45798,"Change":-1.06},"ATAALTIN":{"Buying":44942.64,"Type":"Gold","Name":"ATAALTIN","Selling":46083.19,"Change":-0.91},"14AYARALTIN":{"Buying":3881.41,"Type":"Gold","Name":"14AYARALTIN","Selling":3885.71,"Change":-0.91},"18AYARALTIN":{"Buying":4970.93,"Type":"Gold","Name":"18AYARALTIN","Selling":4976.44,"Change":-0.91},"YIA":{"Buying":6210.26,"Type":"Gold","Name":"22AYARBILEZIK","Selling":6217.14,"Change":-0.91},"IKIBUCUKALTIN":{"Buying":108951.86,"Type":"Gold","Name":"IKIBUCUKALTIN","Selling":110708.73,"Change":-0.91},"BESLIALTIN":{"Buying":220627.51,"Type":"Gold","Name":"BESLIALTIN","Selling":224962.32,"Change":-0.91},"GREMSEALTIN":{"Buying":108951.86,"Type":"Gold","Name":"GREMSEALTIN","Selling":111458.6,"Change":-0.91},"RESATALTIN":{"Buying":44942.64,"Type":"Gold","Name":"RESATALTIN","Selling":46083.19,"Change":-0.91},"HAMITALTIN":{"Buying":44942.64,"Type":"Gold","Name":"HAMITALTIN","Selling":46083.19,"Change":-0.91},"GPL":{"Buying":2913.23,"Type":"Platinum","Name":"GRAMPLATIN","Selling":2920.21,"Change":-2.96},"PAL":{"Buying":2164.26,"Type":"Palladium","Name":"GRAMPALADYUM","Selling":2169.7,"Change":-3.21}}