{"Update_Date":"2026-02-15 22:15:03","USD":{"Type":"Currency","Change":0.19,"Name":"Amerikan Doları","Buying":43.7237,"Selling":43.7339},"EUR":{"Type":"Currency","Change":-0.02,"Name":"Euro","Buying":51.9196,"Selling":51.9339},"GBP":{"Type":"Currency","Change":0.19,"Name":"İngiliz Sterlini","Buying":59.7037,"Selling":59.7357},"CHF":{"Name":"İsviçre Frangı","Buying":56.9254,"Type":"Currency","Selling":56.9699,"Change":0.4},"CAD":{"Name":"Kanada Doları","Buying":32.1026,"Type":"Currency","Selling":32.1195,"Change":0.16},"RUB":{"Name":"Rus Rublesi","Buying":0.5703,"Type":"Currency","Selling":0.5707,"Change":0.94},"AED":{"Name":"BAE Dirhemi","Buying":11.9027,"Type":"Currency","Selling":11.9082,"Change":0.19},"AUD":{"Name":"Avustralya Doları","Buying":30.9258,"Type":"Currency","Selling":30.9461,"Change":0.01},"DKK":{"Name":"Danimarka Kronu","Buying":6.9483,"Type":"Currency","Selling":6.9528,"Change":0.22},"SEK":{"Name":"İsveç Kronu","Buying":4.902,"Type":"Currency","Selling":4.9066,"Change":0.3},"NOK":{"Name":"Norveç Kronu","Buying":4.6025,"Type":"Currency","Selling":4.606,"Change":0.57},"JPY":{"Name":"Japon Yeni","Buying":0.0028599999999999997,"Type":"Currency","Selling":0.002866,"Change":0},"KWD":{"Name":"Kuveyt Dinarı","Buying":142.3742,"Type":"Currency","Selling":142.9017,"Change":0.24},"ZAR":{"Name":"Güney Afrika Randı","Buying":2.7408,"Type":"Currency","Selling":2.743,"Change":0.31},"BHD":{"Name":"Bahreyn Dinarı","Buying":115.9688,"Type":"Currency","Selling":115.9958,"Change":0.18},"LYD":{"Name":"Libya Dinarı","Buying":6.9293,"Type":"Currency","Selling":6.9309,"Change":0.99},"SAR":{"Name":"Suudi Arabistan Riyali","Buying":11.6449,"Type":"Currency","Selling":11.6758,"Change":0.2},"IQD":{"Name":"Irak Dinarı","Buying":0.0334,"Type":"Currency","Selling":0.0334,"Change":0.19},"ILS":{"Name":"İsrail Şekeli","Buying":14.1524,"Type":"Currency","Selling":14.1557,"Change":-0.42},"IRR":{"Name":"İran Riyali","Buying":0.0001,"Type":"Currency","Selling":0.0001,"Change":-99.72},"INR":{"Name":"Hindistan Rupisi","Buying":0.4828,"Type":"Currency","Selling":0.4829,"Change":0.21},"MXN":{"Name":"Meksika Pesosu","Buying":2.5481,"Type":"Currency","Selling":2.5487,"Change":0.69},"HUF":{"Name":"Macar Forinti","Buying":0.1369,"Type":"Currency","Selling":0.1369,"Change":0.18},"NZD":{"Name":"Yeni Zelanda Doları","Buying":26.4192,"Type":"Currency","Selling":26.4253,"Change":0.39},"BRL":{"Name":"Brezilya Reali","Buying":8.3647,"Type":"Currency","Selling":8.3666,"Change":-0.01},"IDR":{"Name":"Endonezya Rupiahi","Buying":0.0026,"Type":"Currency","Selling":0.0026,"Change":0.12},"CZK":{"Name":"Çek Korunası","Buying":2.1389,"Type":"Currency","Selling":2.1394,"Change":0.15},"PLN":{"Name":"Polonya Zlotisi","Buying":12.3332,"Type":"Currency","Selling":12.3361,"Change":0.35},"RON":{"Name":"Romanya Leyi","Buying":10.189,"Type":"Currency","Selling":10.1995,"Change":0.18},"CNY":{"Name":"Çin Yuanı","Buying":6.3338,"Type":"Currency","Selling":6.3373,"Change":0.12},"ARS":{"Name":"Arjantin Pesosu","Buying":0.0312,"Type":"Currency","Selling":0.0313,"Change":0.03},"ALL":{"Name":"Arnavutluk Leki","Buying":0.538,"Type":"Currency","Selling":0.5381,"Change":0.11},"AZN":{"Name":"Azerbaycan Manatı","Buying":25.7198,"Type":"Currency","Selling":25.7258,"Change":0.19},"BAM":{"Name":"Bosna-Hersek Markı","Buying":26.5105,"Type":"Currency","Selling":26.5166,"Change":3.05},"CLP":{"Name":"Şili Pesosu","Buying":0.0507,"Type":"Currency","Selling":0.0507,"Change":-0.23},"COP":{"Name":"Kolombiya Pesosu","Buying":0.0119,"Type":"Currency","Selling":0.0119,"Change":0.3},"CRC":{"Name":"Kostarika Kolonu","Buying":0.0899,"Type":"Currency","Selling":0.0899,"Change":0.78},"DZD":{"Name":"Cezayir Dinarı","Buying":0.3373,"Type":"Currency","Selling":0.3374,"Change":0.18},"EGP":{"Name":"Mısır Lirası","Buying":0.9333,"Type":"Currency","Selling":0.9335,"Change":0.13},"HKD":{"Name":"Hong Kong Doları","Buying":5.593,"Type":"Currency","Selling":5.5943,"Change":0.18},"ISK":{"Name":"İzlanda Kronası","Buying":0.3579,"Type":"Currency","Selling":0.358,"Change":0.33},"KRW":{"Name":"Güney Kore Wonu","Buying":0.0303,"Type":"Currency","Selling":0.0303,"Change":0.17},"KZT":{"Name":"Kazak Tengesi","Buying":0.0884,"Type":"Currency","Selling":0.0884,"Change":0.13},"LBP":{"Name":"Lübnan Lirası","Buying":0.0005,"Type":"Currency","Selling":0.0005,"Change":-4.28},"LKR":{"Name":"Sri Lanka Rupisi","Buying":0.1414,"Type":"Currency","Selling":0.1414,"Change":0.22},"MAD":{"Name":"Fas Dirhemi","Buying":4.784,"Type":"Currency","Selling":4.7852,"Change":0.23},"MDL":{"Name":"Moldovya Leusu","Buying":2.591,"Type":"Currency","Selling":2.5916,"Change":-0.18},"MKD":{"Name":"Makedon Dinarı","Buying":0.842,"Type":"Currency","Selling":0.8422,"Change":0.1},"MYR":{"Name":"Malezya Ringgiti","Buying":11.1928,"Type":"Currency","Selling":11.1954,"Change":0.08},"OMR":{"Name":"Umman Riyali","Buying":113.7187,"Type":"Currency","Selling":113.7452,"Change":0.2},"PEN":{"Name":"Peru İnti","Buying":13.0402,"Type":"Currency","Selling":13.0432,"Change":0.22},"PHP":{"Name":"Filipinler Pesosu","Buying":0.7556,"Type":"Currency","Selling":0.7557,"Change":0.54},"PKR":{"Name":"Pakistan Rupisi","Buying":0.1562,"Type":"Currency","Selling":0.1566,"Change":0.19},"QAR":{"Name":"Katar Riyali","Buying":12.001,"Type":"Currency","Selling":12.0175,"Change":0.19},"RSD":{"Name":"Sırbistan Dinarı","Buying":0.4414,"Type":"Currency","Selling":0.4429,"Change":-0.07},"SGD":{"Name":"Singapur Doları","Buying":34.6436,"Type":"Currency","Selling":34.6517,"Change":0.22},"SYP":{"Name":"Suriye Lirası","Buying":0.3786,"Type":"Currency","Selling":0.3786,"Change":0.2},"THB":{"Name":"Tayland Bahtı","Buying":1.4065,"Type":"Currency","Selling":1.4069,"Change":0.14},"TWD":{"Name":"Yeni Tayvan Doları","Buying":1.3947,"Type":"Currency","Selling":1.395,"Change":0.51},"UAH":{"Name":"Ukrayna Grivnası","Buying":1.0152,"Type":"Currency","Selling":1.0154,"Change":0.13},"UYU":{"Name":"Uruguay Pesosu","Buying":1.1342,"Type":"Currency","Selling":1.1345,"Change":-0.33},"GEL":{"Name":"Gürcistan Larisi","Buying":16.3453,"Type":"Currency","Selling":16.3491,"Change":1.32},"TND":{"Name":"Tunus Dinarı","Buying":15.3794,"Type":"Currency","Selling":15.383,"Change":0.05},"BGN":{"Name":"Bulgar Levası","Buying":26.4336,"Type":"Currency","Selling":26.6537,"Change":-0.1},"GRA":{"Selling":7075.98,"Type":"Gold","Name":"GRAMALTIN","Change":2.56,"Buying":7075.01},"XU100":{"Selling":14180.69,"Type":"Gold","Name":"XU100","Change":0},"DBITCOIN":{"Selling":0,"Type":"Gold","Name":"DBITCOIN","Change":-2.13},"GUMUS":{"Selling":108.35,"Type":"Gold","Name":"GUMUS","Change":3.14,"Buying":108.2},"BRENT":{"Selling":0,"Type":"Gold","Name":"BRENT","Change":-0.04},"ONS":{"Buying":0,"Type":"Gold","Name":"ONS","Selling":0,"Change":2.37},"HAS":{"Buying":7039.63,"Type":"Gold","Name":"GRAMHASALTIN","Selling":7040.6,"Change":2.56},"CEYREKALTIN":{"Buying":11673.05,"Type":"Gold","Name":"CEYREKALTIN","Selling":11955.42,"Change":-0.41},"YARIMALTIN":{"Buying":23273.15,"Type":"Gold","Name":"YARIMALTIN","Selling":23910.85,"Change":-0.41},"TAMALTIN":{"Buying":46692.21,"Type":"Gold","Name":"TAMALTIN","Selling":47675.45,"Change":-0.41},"CUMHURIYETALTINI":{"Buying":48414,"Type":"Gold","Name":"CUMHURIYETALTINI","Selling":49149,"Change":-0.47},"ATAALTIN":{"Buying":48151.34,"Type":"Gold","Name":"ATAALTIN","Selling":49430.38,"Change":-0.41},"14AYARALTIN":{"Buying":4158.53,"Type":"Gold","Name":"14AYARALTIN","Selling":4167.95,"Change":-0.41},"18AYARALTIN":{"Buying":5325.83,"Type":"Gold","Name":"18AYARALTIN","Selling":5337.9,"Change":-0.41},"YIA":{"Buying":6653.64,"Type":"Gold","Name":"22AYARBILEZIK","Selling":6668.71,"Change":-0.41},"IKIBUCUKALTIN":{"Buying":116730.53,"Type":"Gold","Name":"IKIBUCUKALTIN","Selling":118749.9,"Change":-0.41},"BESLIALTIN":{"Buying":236379.32,"Type":"Gold","Name":"BESLIALTIN","Selling":241302.14,"Change":-0.41},"GREMSEALTIN":{"Buying":116730.53,"Type":"Gold","Name":"GREMSEALTIN","Selling":119554.24,"Change":-0.41},"RESATALTIN":{"Buying":48151.34,"Type":"Gold","Name":"RESATALTIN","Selling":49430.38,"Change":-0.41},"HAMITALTIN":{"Buying":48151.34,"Type":"Gold","Name":"HAMITALTIN","Selling":49430.38,"Change":-0.41},"GPL":{"Buying":2900.04,"Type":"Platinum","Name":"GRAMPLATIN","Selling":2906.2,"Change":3.37},"PAL":{"Buying":2378.36,"Type":"Palladium","Name":"GRAMPALADYUM","Selling":2388.11,"Change":4.65},"BTC":{"Name":"Bitcoin","USD_Price":68321,"TRY_Price":2985327,"Selling":2985327,"Change":-2.13,"Type":"CryptoCurrency"},"ETH":{"Name":"Ethereum","USD_Price":1941.5,"TRY_Price":84843,"Selling":84843,"Change":-6.88,"Type":"CryptoCurrency"},"USDT":{"Name":"Tether","USD_Price":0.99966,"TRY_Price":43.59,"Selling":43.59,"Change":-0.01,"Type":"CryptoCurrency"},"XRP":{"Name":"Ripple","USD_Price":1.4646,"TRY_Price":63.97,"Selling":63.97,"Change":-1.68,"Type":"CryptoCurrency"},"BNB":{"Name":"BNB","USD_Price":610.58,"TRY_Price":26674,"Selling":26674,"Change":-3.33,"Type":"CryptoCurrency"},"USDC":{"Name":"USD Coin","USD_Price":1.0004,"TRY_Price":43.71,"Selling":43.71,"Change":0,"Type":"CryptoCurrency"},"SOL":{"Name":"Solana","USD_Price":85.9,"TRY_Price":3753.2,"Selling":3753.2,"Change":-2.38,"Type":"CryptoCurrency"},"TRX":{"Name":"TRON","USD_Price":0.2799,"TRY_Price":12.231,"Selling":12.231,"Change":-1.17,"Type":"CryptoCurrency"},"DOGE":{"Name":"Dogecoin","USD_Price":0.10378,"TRY_Price":4.534,"Selling":4.534,"Change":-3.35,"Type":"CryptoCurrency"},"BCH":{"Name":"Bitcoin Cash","USD_Price":553.1,"TRY_Price":23890,"Selling":23890,"Change":-2.38,"Type":"CryptoCurrency"},"WBT":{"Name":"WhiteBIT Coin","USD_Price":51.09,"TRY_Price":2227.84,"Selling":2227.84,"Change":-2.3,"Type":"CryptoCurrency"},"ADA":{"Name":"Cardano","USD_Price":0.2788,"TRY_Price":12.18,"Selling":12.18,"Change":-5.2,"Type":"CryptoCurrency"},"USDS":{"Name":"USDS","USD_Price":0.99977,"TRY_Price":43.6,"Selling":43.6,"Change":0,"Type":"CryptoCurrency"},"WBTC":{"Name":"Wrapped Bitcoin","USD_Price":68126.21,"TRY_Price":2979077.41,"Selling":2979077.41,"Change":-2.2,"Type":"CryptoCurrency"},"WBETH":{"Name":"Wrapped Beacon ETH","USD_Price":2116.84,"TRY_Price":92566.87,"Selling":92566.87,"Change":-6.84,"Type":"CryptoCurrency"},"LEO":{"Name":"LEO Token","USD_Price":8.44,"TRY_Price":367.96,"Selling":367.96,"Change":-2.76,"Type":"CryptoCurrency"},"HYPE":{"Name":"Hyperliquid","USD_Price":30.67,"TRY_Price":1337.41,"Selling":1337.41,"Change":-1.23,"Type":"CryptoCurrency"},"USDE":{"Name":"Ethena USDe","USD_Price":0.9993,"TRY_Price":43.6982,"Selling":43.6982,"Change":0,"Type":"CryptoCurrency"},"LINK":{"Name":"Chainlink","USD_Price":8.65,"TRY_Price":377.9,"Selling":377.9,"Change":-5.26,"Type":"CryptoCurrency"},"XMR":{"Name":"Monero","USD_Price":333.58,"TRY_Price":14547.08,"Selling":14547.08,"Change":-4.83,"Type":"CryptoCurrency"},"CC":{"Name":"Canton","USD_Price":0.161607,"TRY_Price":7.05,"Selling":7.05,"Change":-2.39,"Type":"CryptoCurrency"},"XLM":{"Name":"Stellar","USD_Price":0.1683,"TRY_Price":7.353,"Selling":7.353,"Change":-3.83,"Type":"CryptoCurrency"},"USD1":{"Name":"USD1","USD_Price":0.9997,"TRY_Price":43.7157,"Selling":43.7157,"Change":-0.02,"Type":"CryptoCurrency"},"ZEC":{"Name":"Zcash","USD_Price":294.32,"TRY_Price":12870.26,"Selling":12870.26,"Change":-0.92,"Type":"CryptoCurrency"},"HBAR":{"Name":"Hedera","USD_Price":0.09835,"TRY_Price":4.296,"Selling":4.296,"Change":-5.65,"Type":"CryptoCurrency"},"LTC":{"Name":"Litecoin","USD_Price":54.45,"TRY_Price":2374,"Selling":2374,"Change":-2.84,"Type":"CryptoCurrency"},"DAI":{"Name":"Dai","USD_Price":0.999643,"TRY_Price":43.59,"Selling":43.59,"Change":-0.01,"Type":"CryptoCurrency"},"PYUSD":{"Name":"PayPal USD","USD_Price":0.999945,"TRY_Price":43.61,"Selling":43.61,"Change":0.05,"Type":"CryptoCurrency"},"AVAX":{"Name":"Avalanche","USD_Price":9.18,"TRY_Price":400.8,"Selling":400.8,"Change":-3.77,"Type":"CryptoCurrency"},"SHIB":{"Name":"Shiba Inu","USD_Price":1.0e-5,"TRY_Price":0.000282,"Selling":0.000282,"Change":-5.97,"Type":"CryptoCurrency"},"SUI":{"Name":"Sui","USD_Price":0.9635,"TRY_Price":42.07,"Selling":42.07,"Change":-6.33,"Type":"CryptoCurrency"},"TON":{"Name":"Toncoin","USD_Price":1.457,"TRY_Price":63.6,"Selling":63.6,"Change":-3.13,"Type":"CryptoCurrency"},"RAIN":{"Name":"Rain","USD_Price":0.00972347,"TRY_Price":0.424026,"Selling":0.424026,"Change":-1.88,"Type":"CryptoCurrency"},"CRO":{"Name":"Cronos","USD_Price":0.079178,"TRY_Price":3.45,"Selling":3.45,"Change":-4.23,"Type":"CryptoCurrency"},"WLFI":{"Name":"World Liberty Financial","USD_Price":0.1,"TRY_Price":4.37,"Selling":4.37,"Change":-8.59,"Type":"CryptoCurrency"},"XAUT":{"Name":"Tether Gold","USD_Price":4998.38,"TRY_Price":217972,"Selling":217972,"Change":0.03,"Type":"CryptoCurrency"},"PAXG":{"Name":"PAX Gold","USD_Price":5026.11,"TRY_Price":219580,"Selling":219580,"Change":-0.07,"Type":"CryptoCurrency"},"M":{"Name":"MemeCore","USD_Price":1.31,"TRY_Price":57.02,"Selling":57.02,"Change":-3.29,"Type":"CryptoCurrency"},"DOT":{"Name":"Polkadot","USD_Price":1.337,"TRY_Price":58.1,"Selling":58.1,"Change":-5.65,"Type":"CryptoCurrency"},"UNI":{"Name":"Uniswap","USD_Price":3.416,"TRY_Price":149.3,"Selling":149.3,"Change":-6.92,"Type":"CryptoCurrency"},"MNT":{"Name":"Mantle","USD_Price":0.626297,"TRY_Price":27.31,"Selling":27.31,"Change":-5.53,"Type":"CryptoCurrency"},"AAVE":{"Name":"Aave","USD_Price":123.75,"TRY_Price":5399,"Selling":5399,"Change":-4.34,"Type":"CryptoCurrency"},"PEPE":{"Name":"Pepe","USD_Price":0,"TRY_Price":0.00019353,"Selling":0.00019353,"Change":-4.32,"Type":"CryptoCurrency"},"ASTER":{"Name":"Aster","USD_Price":0.721,"TRY_Price":31.45,"Selling":31.45,"Change":-1.64,"Type":"CryptoCurrency"},"USDF":{"Name":"Falcon USD","USD_Price":0.997418,"TRY_Price":43.5,"Selling":43.5,"Change":0.03,"Type":"CryptoCurrency"},"TAO":{"Name":"Bittensor","USD_Price":180.8,"TRY_Price":7879,"Selling":7879,"Change":-6.27,"Type":"CryptoCurrency"},"BGB":{"Name":"Bitget Token","USD_Price":2.36,"TRY_Price":102.73,"Selling":102.73,"Change":-2.49,"Type":"CryptoCurrency"},"OKB":{"Name":"OKB","USD_Price":77.93,"TRY_Price":3398.24,"Selling":3398.24,"Change":-3.24,"Type":"CryptoCurrency"},"USDG":{"Name":"Global Dollar","USD_Price":0.999716,"TRY_Price":43.6,"Selling":43.6,"Change":-0.02,"Type":"CryptoCurrency"},"HTX":{"Name":"HTX DAO","USD_Price":0,"TRY_Price":0.0001,"Selling":0.0001,"Change":-0.55,"Type":"CryptoCurrency"}}