{"Update_Date":"2026-03-23 06:21:01","USD":{"Buying":44.3132,"Type":"Currency","Selling":44.3282,"Change":0.05},"EUR":{"Buying":51.2014,"Type":"Currency","Selling":51.2623,"Change":-0.14},"GBP":{"Buying":59.0447,"Type":"Currency","Selling":59.1166,"Change":-0.06},"CHF":{"Buying":56.1353,"Type":"Currency","Selling":56.1756,"Change":-0.13},"CAD":{"Buying":32.3124,"Type":"Currency","Selling":32.3304,"Change":0.11},"RUB":{"Buying":0.5332,"Type":"Currency","Selling":0.5333,"Change":0.23},"AED":{"Buying":12.0626,"Type":"Currency","Selling":12.0739,"Change":0.07},"AUD":{"Buying":30.9395,"Type":"Currency","Selling":30.9588,"Change":-0.52},"DKK":{"Buying":6.8474,"Type":"Currency","Selling":6.8519,"Change":-0.15},"SEK":{"Buying":4.7259,"Type":"Currency","Selling":4.7302,"Change":-0.27},"NOK":{"Buying":4.6175,"Type":"Currency","Selling":4.6263,"Change":-0.2},"JPY":{"Buying":0.002775,"Type":"Currency","Selling":0.0027860000000000003,"Change":0},"KWD":{"Buying":144.2769,"Type":"Currency","Selling":144.8626,"Change":0.04},"ZAR":{"Buying":2.585,"Type":"Currency","Selling":2.5882,"Change":-0.83},"BHD":{"Buying":118.0835,"Type":"Currency","Selling":118.1235,"Change":0.66},"LYD":{"Buying":6.9115,"Type":"Currency","Selling":6.9139,"Change":-0.6},"SAR":{"Buying":11.7998,"Type":"Currency","Selling":11.8073,"Change":0.06},"IQD":{"Buying":0.0338,"Type":"Currency","Selling":0.0338,"Change":-0.1},"ILS":{"Buying":14.1318,"Type":"Currency","Selling":14.1366,"Change":-0.06},"INR":{"Buying":0.4722,"Type":"Currency","Selling":0.4724,"Change":-0.95},"MXN":{"Buying":2.4655,"Type":"Currency","Selling":2.4664,"Change":-0.33},"HUF":{"Buying":0.13,"Type":"Currency","Selling":0.1301,"Change":-0.24},"NZD":{"Buying":25.7605,"Type":"Currency","Selling":25.7692,"Change":-0.25},"BRL":{"Buying":8.3433,"Type":"Currency","Selling":8.3462,"Change":0.04},"IDR":{"Buying":0.0026,"Type":"Currency","Selling":0.0026,"Change":-0.16},"CZK":{"Buying":2.0877,"Type":"Currency","Selling":2.0884,"Change":-0.31},"PLN":{"Buying":11.961,"Type":"Currency","Selling":11.9651,"Change":-0.2},"RON":{"Buying":10.0504,"Type":"Currency","Selling":10.0632,"Change":-0.08},"CNY":{"Buying":6.4082,"Type":"Currency","Selling":6.4105,"Change":-0.08},"ARS":{"Buying":0.032,"Type":"Currency","Selling":0.032,"Change":0.66},"ALL":{"Buying":0.534,"Type":"Currency","Selling":0.5342,"Change":-0.14},"AZN":{"Buying":26.0666,"Type":"Currency","Selling":26.0754,"Change":0.05},"BAM":{"Buying":26.179,"Type":"Currency","Selling":26.1879,"Change":-0.73},"CLP":{"Buying":0.0478,"Type":"Currency","Selling":0.0478,"Change":-1.48},"COP":{"Buying":0.012,"Type":"Currency","Selling":0.012,"Change":0.49},"CRC":{"Buying":0.0948,"Type":"Currency","Selling":0.0948,"Change":0.04},"DZD":{"Buying":0.3355,"Type":"Currency","Selling":0.3356,"Change":0.15},"EGP":{"Buying":0.8483,"Type":"Currency","Selling":0.8485,"Change":0.06},"HKD":{"Buying":5.6583,"Type":"Currency","Selling":5.6602,"Change":0.07},"ISK":{"Buying":0.3558,"Type":"Currency","Selling":0.3559,"Change":-0.1},"KRW":{"Buying":0.0294,"Type":"Currency","Selling":0.0294,"Change":-0.21},"KZT":{"Buying":0.092,"Type":"Currency","Selling":0.0921,"Change":-0.05},"LBP":{"Buying":0.0005,"Type":"Currency","Selling":0.0005,"Change":-0.11},"LKR":{"Buying":0.1421,"Type":"Currency","Selling":0.1422,"Change":-0.08},"MAD":{"Buying":4.7353,"Type":"Currency","Selling":4.7369,"Change":-0.23},"MDL":{"Buying":2.56,"Type":"Currency","Selling":2.5608,"Change":0.05},"MKD":{"Buying":0.8264,"Type":"Currency","Selling":0.8267,"Change":0.07},"MYR":{"Buying":11.2484,"Type":"Currency","Selling":11.2522,"Change":0},"OMR":{"Buying":115.9455,"Type":"Currency","Selling":115.9847,"Change":0.66},"PEN":{"Buying":12.7999,"Type":"Currency","Selling":12.8042,"Change":0.51},"PHP":{"Buying":0.7354,"Type":"Currency","Selling":0.7356,"Change":-0.21},"PKR":{"Buying":0.1577,"Type":"Currency","Selling":0.1593,"Change":-0.13},"QAR":{"Buying":11.6856,"Type":"Currency","Selling":12.549,"Change":-0.31},"RSD":{"Buying":0.4364,"Type":"Currency","Selling":0.4377,"Change":0.07},"SGD":{"Buying":34.5334,"Type":"Currency","Selling":34.545,"Change":-0.03},"SYP":{"Buying":0.3837,"Type":"Currency","Selling":0.3838,"Change":0.05},"THB":{"Buying":1.3415,"Type":"Currency","Selling":1.3419,"Change":-0.36},"TWD":{"Buying":1.38,"Type":"Currency","Selling":1.3805,"Change":-0.23},"UAH":{"Buying":1.0152,"Type":"Currency","Selling":1.0156,"Change":0},"UYU":{"Buying":1.0982,"Type":"Currency","Selling":1.0986,"Change":-0.12},"GEL":{"Buying":16.3216,"Type":"Currency","Selling":16.3271,"Change":-0.32},"TND":{"Buying":14.9859,"Type":"Currency","Selling":14.9909,"Change":-1.57},"BGN":{"Buying":26.125,"Type":"Currency","Selling":26.3851,"Change":1.08},"GRA":{"Selling":6204.4,"Type":"Gold","Name":"GRAMALTIN","Change":-3.16,"Buying":6202.94},"XU100":{"Selling":13047.72,"Type":"Gold","Name":"XU100","Change":-0.51},"DBITCOIN":{"Selling":0,"Type":"Gold","Name":"DBITCOIN","Change":-1.53},"GUMUS":{"Selling":92.69,"Type":"Gold","Name":"GUMUS","Change":-4.05,"Buying":92.55},"BRENT":{"Selling":0,"Type":"Gold","Name":"BRENT","Change":0.52},"ONS":{"Buying":0,"Type":"Gold","Name":"ONS","Selling":0,"Change":-3.2},"HAS":{"Buying":6171.92,"Type":"Gold","Name":"GRAMHASALTIN","Selling":6173.38,"Change":-3.16},"CEYREKALTIN":{"Buying":11186.94,"Type":"Gold","Name":"CEYREKALTIN","Selling":11451.46,"Change":0},"YARIMALTIN":{"Buying":22303.95,"Type":"Gold","Name":"YARIMALTIN","Selling":22902.93,"Change":0},"TAMALTIN":{"Buying":44747.74,"Type":"Gold","Name":"TAMALTIN","Selling":45665.78,"Change":0},"CUMHURIYETALTINI":{"Buying":46391,"Type":"Gold","Name":"CUMHURIYETALTINI","Selling":47091,"Change":-2.47},"ATAALTIN":{"Buying":46146.11,"Type":"Gold","Name":"ATAALTIN","Selling":47346.73,"Change":0},"14AYARALTIN":{"Buying":3985.35,"Type":"Gold","Name":"14AYARALTIN","Selling":3992.25,"Change":0},"18AYARALTIN":{"Buying":5104.04,"Type":"Gold","Name":"18AYARALTIN","Selling":5112.89,"Change":0},"YIA":{"Buying":6376.55,"Type":"Gold","Name":"22AYARBILEZIK","Selling":6387.61,"Change":0},"IKIBUCUKALTIN":{"Buying":111869.36,"Type":"Gold","Name":"IKIBUCUKALTIN","Selling":113744.21,"Change":0},"BESLIALTIN":{"Buying":226535.45,"Type":"Gold","Name":"BESLIALTIN","Selling":231130.48,"Change":0},"GREMSEALTIN":{"Buying":111869.36,"Type":"Gold","Name":"GREMSEALTIN","Selling":114514.65,"Change":0},"RESATALTIN":{"Buying":46146.11,"Type":"Gold","Name":"RESATALTIN","Selling":47346.73,"Change":0},"HAMITALTIN":{"Buying":46146.11,"Type":"Gold","Name":"HAMITALTIN","Selling":47346.73,"Change":0},"GPL":{"Buying":2648.53,"Type":"Platinum","Name":"GRAMPLATIN","Selling":2657.84,"Change":-3.63},"PAL":{"Buying":1994.21,"Type":"Palladium","Name":"GRAMPALADYUM","Selling":1999.16,"Change":-1.01}}