{"Update_Date":"2026-02-21 16:55:01","USD":{"Type":"Currency","Change":0.16,"Name":"Amerikan Doları","Buying":43.8205,"Selling":43.8377},"EUR":{"Type":"Currency","Change":0.16,"Name":"Euro","Buying":51.6883,"Selling":51.7041},"GBP":{"Type":"Currency","Change":0.25,"Name":"İngiliz Sterlini","Buying":59.1478,"Selling":59.1832},"CHF":{"Name":"İsviçre Frangı","Buying":56.5207,"Type":"Currency","Selling":56.5648,"Change":0.2},"CAD":{"Name":"Kanada Doları","Buying":32.0185,"Type":"Currency","Selling":32.0404,"Change":0.25},"RUB":{"Name":"Rus Rublesi","Buying":0.5704,"Type":"Currency","Selling":0.5722,"Change":0.2},"AED":{"Name":"BAE Dirhemi","Buying":11.9301,"Type":"Currency","Selling":11.9357,"Change":0.16},"AUD":{"Name":"Avustralya Doları","Buying":31.0293,"Type":"Currency","Selling":31.0546,"Change":0.55},"DKK":{"Name":"Danimarka Kronu","Buying":6.9115,"Type":"Currency","Selling":6.9165,"Change":0.32},"SEK":{"Name":"İsveç Kronu","Buying":4.8416,"Type":"Currency","Selling":4.8449,"Change":0.36},"NOK":{"Name":"Norveç Kronu","Buying":4.6012,"Type":"Currency","Selling":4.6046,"Change":0.6},"JPY":{"Name":"Japon Yeni","Buying":0.0028260000000000004,"Type":"Currency","Selling":0.002835,"Change":0},"KWD":{"Name":"Kuveyt Dinarı","Buying":142.6836,"Type":"Currency","Selling":143.1973,"Change":0.19},"ZAR":{"Name":"Güney Afrika Randı","Buying":2.7331,"Type":"Currency","Selling":2.7363,"Change":0.97},"BHD":{"Name":"Bahreyn Dinarı","Buying":116.2193,"Type":"Currency","Selling":116.265,"Change":0.16},"LYD":{"Name":"Libya Dinarı","Buying":6.9281,"Type":"Currency","Selling":6.9309,"Change":0.72},"SAR":{"Name":"Suudi Arabistan Riyali","Buying":11.6671,"Type":"Currency","Selling":11.6984,"Change":0.15},"IQD":{"Name":"Irak Dinarı","Buying":0.0334,"Type":"Currency","Selling":0.0335,"Change":0.16},"ILS":{"Name":"İsrail Şekeli","Buying":14.0707,"Type":"Currency","Selling":14.0763,"Change":0.88},"IRR":{"Name":"İran Riyali","Buying":0.0001,"Type":"Currency","Selling":0.0001,"Change":-99.72},"INR":{"Name":"Hindistan Rupisi","Buying":0.4827,"Type":"Currency","Selling":0.4829,"Change":0.47},"MXN":{"Name":"Meksika Pesosu","Buying":2.5602,"Type":"Currency","Selling":2.5612,"Change":0.98},"HUF":{"Name":"Macar Forinti","Buying":0.1359,"Type":"Currency","Selling":0.136,"Change":0.2},"NZD":{"Name":"Yeni Zelanda Doları","Buying":26.1865,"Type":"Currency","Selling":26.1968,"Change":0.26},"BRL":{"Name":"Brezilya Reali","Buying":8.461,"Type":"Currency","Selling":8.4643,"Change":0.96},"IDR":{"Name":"Endonezya Rupiahi","Buying":0.0026,"Type":"Currency","Selling":0.0026,"Change":0.42},"CZK":{"Name":"Çek Korunası","Buying":2.132,"Type":"Currency","Selling":2.1328,"Change":0.39},"PLN":{"Name":"Polonya Zlotisi","Buying":12.2328,"Type":"Currency","Selling":12.2376,"Change":0.33},"RON":{"Name":"Romanya Leyi","Buying":10.1289,"Type":"Currency","Selling":10.1396,"Change":0.3},"CNY":{"Name":"Çin Yuanı","Buying":6.3515,"Type":"Currency","Selling":6.3552,"Change":0.16},"ARS":{"Name":"Arjantin Pesosu","Buying":0.0319,"Type":"Currency","Selling":0.0319,"Change":1.24},"ALL":{"Name":"Arnavutluk Leki","Buying":0.5365,"Type":"Currency","Selling":0.5367,"Change":0.31},"AZN":{"Name":"Azerbaycan Manatı","Buying":25.7768,"Type":"Currency","Selling":25.7869,"Change":0.16},"BAM":{"Name":"Bosna-Hersek Markı","Buying":26.3614,"Type":"Currency","Selling":26.3717,"Change":2.21},"CLP":{"Name":"Şili Pesosu","Buying":0.0506,"Type":"Currency","Selling":0.0507,"Change":0.14},"COP":{"Name":"Kolombiya Pesosu","Buying":0.0118,"Type":"Currency","Selling":0.0118,"Change":0},"CRC":{"Name":"Kostarika Kolonu","Buying":0.0918,"Type":"Currency","Selling":0.0919,"Change":1.05},"DZD":{"Name":"Cezayir Dinarı","Buying":0.337,"Type":"Currency","Selling":0.3371,"Change":0.16},"EGP":{"Name":"Mısır Lirası","Buying":0.9216,"Type":"Currency","Selling":0.922,"Change":0.11},"HKD":{"Name":"Hong Kong Doları","Buying":5.6077,"Type":"Currency","Selling":5.6099,"Change":0.16},"ISK":{"Name":"İzlanda Kronası","Buying":0.3564,"Type":"Currency","Selling":0.3565,"Change":0.32},"KRW":{"Name":"Güney Kore Wonu","Buying":0.0303,"Type":"Currency","Selling":0.0303,"Change":0.51},"KZT":{"Name":"Kazak Tengesi","Buying":0.0878,"Type":"Currency","Selling":0.0878,"Change":-1.07},"LBP":{"Name":"Lübnan Lirası","Buying":0.0005,"Type":"Currency","Selling":0.0005,"Change":0.27},"LKR":{"Name":"Sri Lanka Rupisi","Buying":0.1416,"Type":"Currency","Selling":0.1417,"Change":0.14},"MAD":{"Name":"Fas Dirhemi","Buying":4.7762,"Type":"Currency","Selling":4.7781,"Change":0.06},"MDL":{"Name":"Moldovya Leusu","Buying":2.5641,"Type":"Currency","Selling":2.5651,"Change":-0.13},"MKD":{"Name":"Makedon Dinarı","Buying":0.8361,"Type":"Currency","Selling":0.8364,"Change":-0.31},"MYR":{"Name":"Malezya Ringgiti","Buying":11.2297,"Type":"Currency","Selling":11.2341,"Change":0.33},"OMR":{"Name":"Umman Riyali","Buying":113.9675,"Type":"Currency","Selling":114.0122,"Change":0.15},"PEN":{"Name":"Peru İnti","Buying":13.0379,"Type":"Currency","Selling":13.0431,"Change":0.25},"PHP":{"Name":"Filipinler Pesosu","Buying":0.756,"Type":"Currency","Selling":0.7563,"Change":0.3},"PKR":{"Name":"Pakistan Rupisi","Buying":0.1567,"Type":"Currency","Selling":0.157,"Change":0.19},"QAR":{"Name":"Katar Riyali","Buying":12.03,"Type":"Currency","Selling":12.0449,"Change":0.16},"RSD":{"Name":"Sırbistan Dinarı","Buying":0.4393,"Type":"Currency","Selling":0.4413,"Change":0.16},"SGD":{"Name":"Singapur Doları","Buying":34.6024,"Type":"Currency","Selling":34.616,"Change":0.33},"SYP":{"Name":"Suriye Lirası","Buying":0.3794,"Type":"Currency","Selling":0.3795,"Change":0.17},"THB":{"Name":"Tayland Bahtı","Buying":1.4107,"Type":"Currency","Selling":1.4112,"Change":0.59},"TWD":{"Name":"Yeni Tayvan Doları","Buying":1.3898,"Type":"Currency","Selling":1.3903,"Change":0.35},"UAH":{"Name":"Ukrayna Grivnası","Buying":1.0133,"Type":"Currency","Selling":1.0137,"Change":0.16},"UYU":{"Name":"Uruguay Pesosu","Buying":1.1294,"Type":"Currency","Selling":1.1298,"Change":-0.53},"GEL":{"Name":"Gürcistan Larisi","Buying":16.3815,"Type":"Currency","Selling":16.3879,"Change":1.29},"TND":{"Name":"Tunus Dinarı","Buying":15.2898,"Type":"Currency","Selling":15.2958,"Change":-0.08},"BGN":{"Name":"Bulgar Levası","Buying":26.2504,"Type":"Currency","Selling":26.557,"Change":-0.13},"GRA":{"Selling":7183.04,"Type":"Gold","Name":"GRAMALTIN","Change":2.07,"Buying":7182.08},"XU100":{"Selling":13934.06,"Type":"Gold","Name":"XU100","Change":0.94},"DBITCOIN":{"Selling":0,"Type":"Gold","Name":"DBITCOIN","Change":2.2},"GUMUS":{"Selling":119.18,"Type":"Gold","Name":"GUMUS","Change":7.98,"Buying":119.1},"BRENT":{"Selling":0,"Type":"Gold","Name":"BRENT","Change":-0.39},"ONS":{"Buying":0,"Type":"Gold","Name":"ONS","Selling":0,"Change":1.9},"HAS":{"Buying":7146.17,"Type":"Gold","Name":"GRAMHASALTIN","Selling":7147.13,"Change":2.07},"CEYREKALTIN":{"Buying":11729.31,"Type":"Gold","Name":"CEYREKALTIN","Selling":12005.75,"Change":0.51},"YARIMALTIN":{"Buying":23385.31,"Type":"Gold","Name":"YARIMALTIN","Selling":24011.5,"Change":0.51},"TAMALTIN":{"Buying":46917.24,"Type":"Gold","Name":"TAMALTIN","Selling":47876.13,"Change":0.51},"CUMHURIYETALTINI":{"Buying":48644,"Type":"Gold","Name":"CUMHURIYETALTINI","Selling":49379,"Change":0.51},"ATAALTIN":{"Buying":48383.4,"Type":"Gold","Name":"ATAALTIN","Selling":49638.44,"Change":0.51},"14AYARALTIN":{"Buying":4178.57,"Type":"Gold","Name":"14AYARALTIN","Selling":4185.49,"Change":0.51},"18AYARALTIN":{"Buying":5351.5,"Type":"Gold","Name":"18AYARALTIN","Selling":5360.36,"Change":0.51},"YIA":{"Buying":6685.71,"Type":"Gold","Name":"22AYARBILEZIK","Selling":6696.78,"Change":0.51},"IKIBUCUKALTIN":{"Buying":117293.09,"Type":"Gold","Name":"IKIBUCUKALTIN","Selling":119249.75,"Change":0.51},"BESLIALTIN":{"Buying":237518.5,"Type":"Gold","Name":"BESLIALTIN","Selling":242317.85,"Change":0.51},"GREMSEALTIN":{"Buying":117293.09,"Type":"Gold","Name":"GREMSEALTIN","Selling":120057.48,"Change":0.51},"RESATALTIN":{"Buying":48383.4,"Type":"Gold","Name":"RESATALTIN","Selling":49638.44,"Change":0.51},"HAMITALTIN":{"Buying":48383.4,"Type":"Gold","Name":"HAMITALTIN","Selling":49638.44,"Change":0.51},"GPL":{"Buying":3048.63,"Type":"Platinum","Name":"GRAMPLATIN","Selling":3054.77,"Change":4.39},"PAL":{"Buying":2471.52,"Type":"Palladium","Name":"GRAMPALADYUM","Selling":2477.76,"Change":4.1},"BTC":{"Name":"Bitcoin","USD_Price":68242,"TRY_Price":2983640,"Selling":2983640,"Change":2.2,"Type":"CryptoCurrency"},"ETH":{"Name":"Ethereum","USD_Price":1980.8,"TRY_Price":86619,"Selling":86619,"Change":2.59,"Type":"CryptoCurrency"},"USDT":{"Name":"Tether","USD_Price":0.999759,"TRY_Price":43.82,"Selling":43.82,"Change":0,"Type":"CryptoCurrency"},"XRP":{"Name":"Ripple","USD_Price":1.4413,"TRY_Price":63.04,"Selling":63.04,"Change":3.98,"Type":"CryptoCurrency"},"BNB":{"Name":"BNB","USD_Price":631.3,"TRY_Price":27600,"Selling":27600,"Change":4.66,"Type":"CryptoCurrency"},"USDC":{"Name":"USD Coin","USD_Price":1.0002,"TRY_Price":43.75,"Selling":43.75,"Change":-0.02,"Type":"CryptoCurrency"},"SOL":{"Name":"Solana","USD_Price":85.41,"TRY_Price":3736.5,"Selling":3736.5,"Change":3.98,"Type":"CryptoCurrency"},"TRX":{"Name":"TRON","USD_Price":0.286,"TRY_Price":12.504,"Selling":12.504,"Change":0.42,"Type":"CryptoCurrency"},"DOGE":{"Name":"Dogecoin","USD_Price":0.10024,"TRY_Price":4.383,"Selling":4.383,"Change":4.22,"Type":"CryptoCurrency"},"BCH":{"Name":"Bitcoin Cash","USD_Price":569.7,"TRY_Price":24911,"Selling":24911,"Change":4.49,"Type":"CryptoCurrency"},"WBT":{"Name":"WhiteBIT Coin","USD_Price":50.88,"TRY_Price":2230.23,"Selling":2230.23,"Change":1.65,"Type":"CryptoCurrency"},"ADA":{"Name":"Cardano","USD_Price":0.283,"TRY_Price":12.36,"Selling":12.36,"Change":4.27,"Type":"CryptoCurrency"},"USDS":{"Name":"USDS","USD_Price":0.999932,"TRY_Price":43.83,"Selling":43.83,"Change":-0.01,"Type":"CryptoCurrency"},"WBTC":{"Name":"Wrapped Bitcoin","USD_Price":68020.76,"TRY_Price":2981281.89,"Selling":2981281.89,"Change":2.18,"Type":"CryptoCurrency"},"WBETH":{"Name":"Wrapped Beacon ETH","USD_Price":2158.68,"TRY_Price":94612.79,"Selling":94612.79,"Change":2.49,"Type":"CryptoCurrency"},"LEO":{"Name":"LEO Token","USD_Price":8.65,"TRY_Price":379.14,"Selling":379.14,"Change":-0.66,"Type":"CryptoCurrency"},"HYPE":{"Name":"Hyperliquid","USD_Price":29.87,"TRY_Price":1309.25,"Selling":1309.25,"Change":2.98,"Type":"CryptoCurrency"},"LINK":{"Name":"Chainlink","USD_Price":8.95,"TRY_Price":391.3,"Selling":391.3,"Change":5.42,"Type":"CryptoCurrency"},"USDE":{"Name":"Ethena USDe","USD_Price":0.9994,"TRY_Price":43.8027,"Selling":43.8027,"Change":0,"Type":"CryptoCurrency"},"CC":{"Name":"Canton","USD_Price":0.161409,"TRY_Price":7.07,"Selling":7.07,"Change":2.35,"Type":"CryptoCurrency"},"XMR":{"Name":"Monero","USD_Price":328.09,"TRY_Price":14380.16,"Selling":14380.16,"Change":-0.63,"Type":"CryptoCurrency"},"XLM":{"Name":"Stellar","USD_Price":0.1633,"TRY_Price":7.126,"Selling":7.126,"Change":3.22,"Type":"CryptoCurrency"},"USD1":{"Name":"USD1","USD_Price":0.9994,"TRY_Price":43.8027,"Selling":43.8027,"Change":0.01,"Type":"CryptoCurrency"},"RAIN":{"Name":"Rain","USD_Price":0.00956274,"TRY_Price":0.419183,"Selling":0.419183,"Change":0.45,"Type":"CryptoCurrency"},"HBAR":{"Name":"Hedera","USD_Price":0.10041,"TRY_Price":4.391,"Selling":4.391,"Change":3.27,"Type":"CryptoCurrency"},"ZEC":{"Name":"Zcash","USD_Price":259.87,"TRY_Price":11389.84,"Selling":11389.84,"Change":1.97,"Type":"CryptoCurrency"},"LTC":{"Name":"Litecoin","USD_Price":55.34,"TRY_Price":2418,"Selling":2418,"Change":4.4,"Type":"CryptoCurrency"},"DAI":{"Name":"Dai","USD_Price":0.99954,"TRY_Price":43.81,"Selling":43.81,"Change":-0.06,"Type":"CryptoCurrency"},"PYUSD":{"Name":"PayPal USD","USD_Price":0.999639,"TRY_Price":43.81,"Selling":43.81,"Change":-0.03,"Type":"CryptoCurrency"},"AVAX":{"Name":"Avalanche","USD_Price":9.33,"TRY_Price":408,"Selling":408,"Change":4.01,"Type":"CryptoCurrency"},"SHIB":{"Name":"Shiba Inu","USD_Price":1.0e-5,"TRY_Price":0.0002836,"Selling":0.0002836,"Change":4.85,"Type":"CryptoCurrency"},"SUI":{"Name":"Sui","USD_Price":0.9587,"TRY_Price":41.83,"Selling":41.83,"Change":4.04,"Type":"CryptoCurrency"},"TON":{"Name":"Toncoin","USD_Price":1.335,"TRY_Price":58.3,"Selling":58.3,"Change":0.23,"Type":"CryptoCurrency"},"WLFI":{"Name":"World Liberty Financial","USD_Price":0.1218,"TRY_Price":5.324,"Selling":5.324,"Change":5.09,"Type":"CryptoCurrency"},"CRO":{"Name":"Cronos","USD_Price":0.07823,"TRY_Price":3.43,"Selling":3.43,"Change":0.73,"Type":"CryptoCurrency"},"XAUT":{"Name":"Tether Gold","USD_Price":5095.83,"TRY_Price":223351,"Selling":223351,"Change":1.73,"Type":"CryptoCurrency"},"PAXG":{"Name":"PAX Gold","USD_Price":5133.7,"TRY_Price":224520,"Selling":224520,"Change":1.45,"Type":"CryptoCurrency"},"M":{"Name":"MemeCore","USD_Price":1.33,"TRY_Price":58.14,"Selling":58.14,"Change":-1.05,"Type":"CryptoCurrency"},"UNI":{"Name":"Uniswap","USD_Price":3.641,"TRY_Price":159.1,"Selling":159.1,"Change":9.08,"Type":"CryptoCurrency"},"DOT":{"Name":"Polkadot","USD_Price":1.38,"TRY_Price":60.3,"Selling":60.3,"Change":7.48,"Type":"CryptoCurrency"},"MNT":{"Name":"Mantle","USD_Price":0.63681,"TRY_Price":27.91,"Selling":27.91,"Change":3.13,"Type":"CryptoCurrency"},"AAVE":{"Name":"Aave","USD_Price":122.91,"TRY_Price":5376,"Selling":5376,"Change":4.36,"Type":"CryptoCurrency"},"PEPE":{"Name":"Pepe","USD_Price":0,"TRY_Price":0.00018746,"Selling":0.00018746,"Change":4.63,"Type":"CryptoCurrency"},"ASTER":{"Name":"Aster","USD_Price":0.723,"TRY_Price":31.66,"Selling":31.66,"Change":3.88,"Type":"CryptoCurrency"},"USDF":{"Name":"Falcon USD","USD_Price":0.996973,"TRY_Price":43.7,"Selling":43.7,"Change":-0.01,"Type":"CryptoCurrency"},"TAO":{"Name":"Bittensor","USD_Price":182.7,"TRY_Price":7990,"Selling":7990,"Change":4.94,"Type":"CryptoCurrency"},"OKB":{"Name":"OKB","USD_Price":80.49,"TRY_Price":3527.79,"Selling":3527.79,"Change":3.25,"Type":"CryptoCurrency"},"BGB":{"Name":"Bitget Token","USD_Price":2.33,"TRY_Price":102.01,"Selling":102.01,"Change":-0.13,"Type":"CryptoCurrency"},"USDG":{"Name":"Global Dollar","USD_Price":0.999942,"TRY_Price":43.83,"Selling":43.83,"Change":0.01,"Type":"CryptoCurrency"},"PI":{"Name":"Pi Network","USD_Price":0.174898,"TRY_Price":7.67,"Selling":7.67,"Change":2.15,"Type":"CryptoCurrency"}}